package unk.com.zing.zalo.ui;

class ck
  implements Runnable
{
  ck(BroadcastSMSInviteToFriendsActivity paramBroadcastSMSInviteToFriendsActivity)
  {
  }

  // ERROR //
  public void run()
  {
    // Byte code:
    //   0: iconst_0
    //   1: istore_1
    //   2: new 22	com/zing/zalo/control/af
    //   5: dup
    //   6: invokespecial 23	com/zing/zalo/control/af:<init>	()V
    //   9: astore_2
    //   10: aload_0
    //   11: getfield 12	com/zing/zalo/ui/ck:aaB	Lcom/zing/zalo/ui/BroadcastSMSInviteToFriendsActivity;
    //   14: iconst_0
    //   15: invokestatic 29	com/zing/zalo/ui/BroadcastSMSInviteToFriendsActivity:d	(Lcom/zing/zalo/ui/BroadcastSMSInviteToFriendsActivity;I)V
    //   18: iconst_m1
    //   19: istore 5
    //   21: iconst_0
    //   22: istore 6
    //   24: getstatic 35	com/zing/zalo/g/a:Dy	Ljava/util/List;
    //   27: invokeinterface 41 1 0
    //   32: istore 7
    //   34: iload_1
    //   35: iload 7
    //   37: if_icmplt +20 -> 57
    //   40: aload_0
    //   41: getfield 12	com/zing/zalo/ui/ck:aaB	Lcom/zing/zalo/ui/BroadcastSMSInviteToFriendsActivity;
    //   44: new 43	com/zing/zalo/ui/cl
    //   47: dup
    //   48: aload_0
    //   49: aload_2
    //   50: invokespecial 46	com/zing/zalo/ui/cl:<init>	(Lcom/zing/zalo/ui/ck;Lcom/zing/zalo/control/af;)V
    //   53: invokevirtual 50	com/zing/zalo/ui/BroadcastSMSInviteToFriendsActivity:runOnUiThread	(Ljava/lang/Runnable;)V
    //   56: return
    //   57: getstatic 35	com/zing/zalo/g/a:Dy	Ljava/util/List;
    //   60: iload_1
    //   61: invokeinterface 54 2 0
    //   66: checkcast 56	com/zing/zalo/control/ae
    //   69: astore 8
    //   71: new 58	com/zing/zalo/control/w
    //   74: dup
    //   75: invokespecial 59	com/zing/zalo/control/w:<init>	()V
    //   78: astore 9
    //   80: aload 9
    //   82: ldc 61
    //   84: putfield 65	com/zing/zalo/control/w:xU	Ljava/lang/String;
    //   87: aload 9
    //   89: aload 8
    //   91: invokevirtual 69	com/zing/zalo/control/ae:getDisplayName	()Ljava/lang/String;
    //   94: putfield 72	com/zing/zalo/control/w:xV	Ljava/lang/String;
    //   97: aload 9
    //   99: aload 8
    //   101: invokevirtual 75	com/zing/zalo/control/ae:gy	()Ljava/lang/String;
    //   104: putfield 78	com/zing/zalo/control/w:ya	Ljava/lang/String;
    //   107: aload 9
    //   109: aload 8
    //   111: invokevirtual 81	com/zing/zalo/control/ae:gz	()Ljava/lang/String;
    //   114: putfield 84	com/zing/zalo/control/w:za	Ljava/lang/String;
    //   117: getstatic 88	com/zing/zalo/g/a:DK	Ljava/util/HashMap;
    //   120: aload 8
    //   122: invokevirtual 81	com/zing/zalo/control/ae:gz	()Ljava/lang/String;
    //   125: invokevirtual 94	java/util/HashMap:containsKey	(Ljava/lang/Object;)Z
    //   128: ifne +612 -> 740
    //   131: getstatic 97	com/zing/zalo/g/a:Cq	Ljava/lang/String;
    //   134: aload 8
    //   136: invokevirtual 75	com/zing/zalo/control/ae:gy	()Ljava/lang/String;
    //   139: invokestatic 103	com/zing/zalo/utils/a/d:am	(Ljava/lang/String;Ljava/lang/String;)Z
    //   142: ifeq +14 -> 156
    //   145: iload 5
    //   147: istore 17
    //   149: iload 6
    //   151: istore 18
    //   153: goto +595 -> 748
    //   156: aload 9
    //   158: getfield 84	com/zing/zalo/control/w:za	Ljava/lang/String;
    //   161: invokevirtual 108	java/lang/String:trim	()Ljava/lang/String;
    //   164: ldc 61
    //   166: invokevirtual 111	java/lang/String:equals	(Ljava/lang/Object;)Z
    //   169: ifne +571 -> 740
    //   172: aload 9
    //   174: getfield 84	com/zing/zalo/control/w:za	Ljava/lang/String;
    //   177: invokevirtual 108	java/lang/String:trim	()Ljava/lang/String;
    //   180: getstatic 114	com/zing/zalo/utils/a/d:aEr	Ljava/lang/String;
    //   183: invokevirtual 118	java/lang/String:equalsIgnoreCase	(Ljava/lang/String;)Z
    //   186: ifne +554 -> 740
    //   189: aload_2
    //   190: aload 9
    //   192: getfield 84	com/zing/zalo/control/w:za	Ljava/lang/String;
    //   195: invokevirtual 121	com/zing/zalo/control/af:aR	(Ljava/lang/String;)Z
    //   198: istore 27
    //   200: iload 27
    //   202: ifeq +21 -> 223
    //   205: iload 5
    //   207: istore 17
    //   209: iload 6
    //   211: istore 18
    //   213: goto +535 -> 748
    //   216: astore 10
    //   218: aload 10
    //   220: invokevirtual 124	java/lang/Exception:printStackTrace	()V
    //   223: aload 8
    //   225: invokevirtual 69	com/zing/zalo/control/ae:getDisplayName	()Ljava/lang/String;
    //   228: invokestatic 130	com/zing/zalo/utils/p:eN	(Ljava/lang/String;)Ljava/lang/String;
    //   231: invokevirtual 108	java/lang/String:trim	()Ljava/lang/String;
    //   234: invokevirtual 133	java/lang/String:toUpperCase	()Ljava/lang/String;
    //   237: iconst_0
    //   238: invokevirtual 137	java/lang/String:charAt	(I)C
    //   241: istore 11
    //   243: iload 5
    //   245: iconst_1
    //   246: iadd
    //   247: istore 12
    //   249: iload 12
    //   251: ifeq +290 -> 541
    //   254: getstatic 35	com/zing/zalo/g/a:Dy	Ljava/util/List;
    //   257: iload 6
    //   259: invokeinterface 54 2 0
    //   264: checkcast 56	com/zing/zalo/control/ae
    //   267: invokevirtual 69	com/zing/zalo/control/ae:getDisplayName	()Ljava/lang/String;
    //   270: invokestatic 130	com/zing/zalo/utils/p:eN	(Ljava/lang/String;)Ljava/lang/String;
    //   273: invokevirtual 108	java/lang/String:trim	()Ljava/lang/String;
    //   276: invokevirtual 133	java/lang/String:toUpperCase	()Ljava/lang/String;
    //   279: iconst_0
    //   280: invokevirtual 137	java/lang/String:charAt	(I)C
    //   283: istore 22
    //   285: ldc 139
    //   287: iload 22
    //   289: invokevirtual 143	java/lang/String:indexOf	(I)I
    //   292: iconst_m1
    //   293: if_icmpeq +145 -> 438
    //   296: iload 11
    //   298: iload 22
    //   300: if_icmple +103 -> 403
    //   303: ldc 139
    //   305: iload 11
    //   307: invokevirtual 143	java/lang/String:indexOf	(I)I
    //   310: iconst_m1
    //   311: if_icmpeq +92 -> 403
    //   314: new 58	com/zing/zalo/control/w
    //   317: dup
    //   318: invokespecial 59	com/zing/zalo/control/w:<init>	()V
    //   321: astore 23
    //   323: aload 23
    //   325: ldc 61
    //   327: putfield 65	com/zing/zalo/control/w:xU	Ljava/lang/String;
    //   330: aload 23
    //   332: new 145	java/lang/StringBuilder
    //   335: dup
    //   336: invokespecial 146	java/lang/StringBuilder:<init>	()V
    //   339: iload 11
    //   341: invokevirtual 150	java/lang/StringBuilder:append	(C)Ljava/lang/StringBuilder;
    //   344: invokevirtual 153	java/lang/StringBuilder:toString	()Ljava/lang/String;
    //   347: putfield 72	com/zing/zalo/control/w:xV	Ljava/lang/String;
    //   350: aload 23
    //   352: iconst_0
    //   353: invokevirtual 157	com/zing/zalo/control/w:B	(Z)V
    //   356: aload 23
    //   358: new 145	java/lang/StringBuilder
    //   361: dup
    //   362: invokespecial 146	java/lang/StringBuilder:<init>	()V
    //   365: iload 11
    //   367: invokevirtual 150	java/lang/StringBuilder:append	(C)Ljava/lang/StringBuilder;
    //   370: invokevirtual 153	java/lang/StringBuilder:toString	()Ljava/lang/String;
    //   373: putfield 78	com/zing/zalo/control/w:ya	Ljava/lang/String;
    //   376: aload 23
    //   378: new 145	java/lang/StringBuilder
    //   381: dup
    //   382: invokespecial 146	java/lang/StringBuilder:<init>	()V
    //   385: iload 11
    //   387: invokevirtual 150	java/lang/StringBuilder:append	(C)Ljava/lang/StringBuilder;
    //   390: invokevirtual 153	java/lang/StringBuilder:toString	()Ljava/lang/String;
    //   393: putfield 84	com/zing/zalo/control/w:za	Ljava/lang/String;
    //   396: aload_2
    //   397: aload 23
    //   399: invokevirtual 160	com/zing/zalo/control/af:a	(Lcom/zing/zalo/control/w;)Z
    //   402: pop
    //   403: aload_2
    //   404: aload 9
    //   406: invokevirtual 160	com/zing/zalo/control/af:a	(Lcom/zing/zalo/control/w;)Z
    //   409: pop
    //   410: aload_0
    //   411: getfield 12	com/zing/zalo/ui/ck:aaB	Lcom/zing/zalo/ui/BroadcastSMSInviteToFriendsActivity;
    //   414: astore 16
    //   416: aload 16
    //   418: iconst_1
    //   419: aload 16
    //   421: invokestatic 164	com/zing/zalo/ui/BroadcastSMSInviteToFriendsActivity:r	(Lcom/zing/zalo/ui/BroadcastSMSInviteToFriendsActivity;)I
    //   424: iadd
    //   425: invokestatic 29	com/zing/zalo/ui/BroadcastSMSInviteToFriendsActivity:d	(Lcom/zing/zalo/ui/BroadcastSMSInviteToFriendsActivity;I)V
    //   428: iload 12
    //   430: istore 17
    //   432: iload_1
    //   433: istore 18
    //   435: goto +313 -> 748
    //   438: ldc 139
    //   440: iload 11
    //   442: invokevirtual 143	java/lang/String:indexOf	(I)I
    //   445: iconst_m1
    //   446: if_icmpeq -43 -> 403
    //   449: new 58	com/zing/zalo/control/w
    //   452: dup
    //   453: invokespecial 59	com/zing/zalo/control/w:<init>	()V
    //   456: astore 25
    //   458: aload 25
    //   460: ldc 61
    //   462: putfield 65	com/zing/zalo/control/w:xU	Ljava/lang/String;
    //   465: aload 25
    //   467: new 145	java/lang/StringBuilder
    //   470: dup
    //   471: invokespecial 146	java/lang/StringBuilder:<init>	()V
    //   474: iload 11
    //   476: invokevirtual 150	java/lang/StringBuilder:append	(C)Ljava/lang/StringBuilder;
    //   479: invokevirtual 153	java/lang/StringBuilder:toString	()Ljava/lang/String;
    //   482: putfield 72	com/zing/zalo/control/w:xV	Ljava/lang/String;
    //   485: aload 25
    //   487: iconst_0
    //   488: invokevirtual 157	com/zing/zalo/control/w:B	(Z)V
    //   491: aload 25
    //   493: new 145	java/lang/StringBuilder
    //   496: dup
    //   497: invokespecial 146	java/lang/StringBuilder:<init>	()V
    //   500: iload 11
    //   502: invokevirtual 150	java/lang/StringBuilder:append	(C)Ljava/lang/StringBuilder;
    //   505: invokevirtual 153	java/lang/StringBuilder:toString	()Ljava/lang/String;
    //   508: putfield 78	com/zing/zalo/control/w:ya	Ljava/lang/String;
    //   511: aload 25
    //   513: new 145	java/lang/StringBuilder
    //   516: dup
    //   517: invokespecial 146	java/lang/StringBuilder:<init>	()V
    //   520: iload 11
    //   522: invokevirtual 150	java/lang/StringBuilder:append	(C)Ljava/lang/StringBuilder;
    //   525: invokevirtual 153	java/lang/StringBuilder:toString	()Ljava/lang/String;
    //   528: putfield 84	com/zing/zalo/control/w:za	Ljava/lang/String;
    //   531: aload_2
    //   532: aload 25
    //   534: invokevirtual 160	com/zing/zalo/control/af:a	(Lcom/zing/zalo/control/w;)Z
    //   537: pop
    //   538: goto -135 -> 403
    //   541: ldc 139
    //   543: iload 11
    //   545: invokevirtual 143	java/lang/String:indexOf	(I)I
    //   548: iconst_m1
    //   549: if_icmpne +77 -> 626
    //   552: new 58	com/zing/zalo/control/w
    //   555: dup
    //   556: invokespecial 59	com/zing/zalo/control/w:<init>	()V
    //   559: astore 13
    //   561: aload 13
    //   563: ldc 61
    //   565: putfield 65	com/zing/zalo/control/w:xU	Ljava/lang/String;
    //   568: aload 13
    //   570: ldc 166
    //   572: putfield 72	com/zing/zalo/control/w:xV	Ljava/lang/String;
    //   575: aload 13
    //   577: iconst_0
    //   578: invokevirtual 157	com/zing/zalo/control/w:B	(Z)V
    //   581: aload 13
    //   583: ldc 166
    //   585: putfield 78	com/zing/zalo/control/w:ya	Ljava/lang/String;
    //   588: aload 13
    //   590: ldc 166
    //   592: putfield 84	com/zing/zalo/control/w:za	Ljava/lang/String;
    //   595: aload_2
    //   596: aload 13
    //   598: invokevirtual 160	com/zing/zalo/control/af:a	(Lcom/zing/zalo/control/w;)Z
    //   601: pop
    //   602: goto -199 -> 403
    //   605: astore 4
    //   607: aload_0
    //   608: getfield 12	com/zing/zalo/ui/ck:aaB	Lcom/zing/zalo/ui/BroadcastSMSInviteToFriendsActivity;
    //   611: new 43	com/zing/zalo/ui/cl
    //   614: dup
    //   615: aload_0
    //   616: aload_2
    //   617: invokespecial 46	com/zing/zalo/ui/cl:<init>	(Lcom/zing/zalo/ui/ck;Lcom/zing/zalo/control/af;)V
    //   620: invokevirtual 50	com/zing/zalo/ui/BroadcastSMSInviteToFriendsActivity:runOnUiThread	(Ljava/lang/Runnable;)V
    //   623: aload 4
    //   625: athrow
    //   626: new 58	com/zing/zalo/control/w
    //   629: dup
    //   630: invokespecial 59	com/zing/zalo/control/w:<init>	()V
    //   633: astore 20
    //   635: aload 20
    //   637: ldc 61
    //   639: putfield 65	com/zing/zalo/control/w:xU	Ljava/lang/String;
    //   642: aload 20
    //   644: new 145	java/lang/StringBuilder
    //   647: dup
    //   648: invokespecial 146	java/lang/StringBuilder:<init>	()V
    //   651: iload 11
    //   653: invokevirtual 150	java/lang/StringBuilder:append	(C)Ljava/lang/StringBuilder;
    //   656: invokevirtual 153	java/lang/StringBuilder:toString	()Ljava/lang/String;
    //   659: putfield 72	com/zing/zalo/control/w:xV	Ljava/lang/String;
    //   662: aload 20
    //   664: iconst_0
    //   665: invokevirtual 157	com/zing/zalo/control/w:B	(Z)V
    //   668: aload 20
    //   670: new 145	java/lang/StringBuilder
    //   673: dup
    //   674: invokespecial 146	java/lang/StringBuilder:<init>	()V
    //   677: iload 11
    //   679: invokevirtual 150	java/lang/StringBuilder:append	(C)Ljava/lang/StringBuilder;
    //   682: invokevirtual 153	java/lang/StringBuilder:toString	()Ljava/lang/String;
    //   685: putfield 78	com/zing/zalo/control/w:ya	Ljava/lang/String;
    //   688: aload 20
    //   690: new 145	java/lang/StringBuilder
    //   693: dup
    //   694: invokespecial 146	java/lang/StringBuilder:<init>	()V
    //   697: iload 11
    //   699: invokevirtual 150	java/lang/StringBuilder:append	(C)Ljava/lang/StringBuilder;
    //   702: invokevirtual 153	java/lang/StringBuilder:toString	()Ljava/lang/String;
    //   705: putfield 84	com/zing/zalo/control/w:za	Ljava/lang/String;
    //   708: aload_2
    //   709: aload 20
    //   711: invokevirtual 160	com/zing/zalo/control/af:a	(Lcom/zing/zalo/control/w;)Z
    //   714: pop
    //   715: goto -312 -> 403
    //   718: astore_3
    //   719: aload_3
    //   720: invokevirtual 124	java/lang/Exception:printStackTrace	()V
    //   723: aload_0
    //   724: getfield 12	com/zing/zalo/ui/ck:aaB	Lcom/zing/zalo/ui/BroadcastSMSInviteToFriendsActivity;
    //   727: new 43	com/zing/zalo/ui/cl
    //   730: dup
    //   731: aload_0
    //   732: aload_2
    //   733: invokespecial 46	com/zing/zalo/ui/cl:<init>	(Lcom/zing/zalo/ui/ck;Lcom/zing/zalo/control/af;)V
    //   736: invokevirtual 50	com/zing/zalo/ui/BroadcastSMSInviteToFriendsActivity:runOnUiThread	(Ljava/lang/Runnable;)V
    //   739: return
    //   740: iload 5
    //   742: istore 17
    //   744: iload 6
    //   746: istore 18
    //   748: iinc 1 1
    //   751: iload 18
    //   753: istore 6
    //   755: iload 17
    //   757: istore 5
    //   759: goto -735 -> 24
    //   762: astore 19
    //   764: goto -361 -> 403
    //
    // Exception table:
    //   from	to	target	type
    //   117	145	216	java/lang/Exception
    //   156	200	216	java/lang/Exception
    //   10	18	605	finally
    //   24	34	605	finally
    //   57	117	605	finally
    //   117	145	605	finally
    //   156	200	605	finally
    //   218	223	605	finally
    //   223	243	605	finally
    //   254	296	605	finally
    //   303	403	605	finally
    //   403	428	605	finally
    //   438	538	605	finally
    //   541	602	605	finally
    //   626	715	605	finally
    //   719	723	605	finally
    //   10	18	718	java/lang/Exception
    //   24	34	718	java/lang/Exception
    //   57	117	718	java/lang/Exception
    //   218	223	718	java/lang/Exception
    //   223	243	718	java/lang/Exception
    //   403	428	718	java/lang/Exception
    //   254	296	762	java/lang/Exception
    //   303	403	762	java/lang/Exception
    //   438	538	762	java/lang/Exception
    //   541	602	762	java/lang/Exception
    //   626	715	762	java/lang/Exception
  }
}

/* Location:           /home/danghvu/0day/Zalo/Zalo_1.0.8_dex2jar.jar
 * Qualified Name:     com.zing.zalo.ui.ck
 * JD-Core Version:    0.6.2
 */