package unk.com.zing.zalo.ui;

import android.view.View.OnTouchListener;

class dl
  implements View.OnTouchListener
{
  dl(ChatActivity paramChatActivity)
  {
  }

  // ERROR //
  public boolean onTouch(android.view.View paramView, android.view.MotionEvent paramMotionEvent)
  {
    // Byte code:
    //   0: aload_0
    //   1: getfield 12	com/zing/zalo/ui/dl:acV	Lcom/zing/zalo/ui/ChatActivity;
    //   4: getfield 27	com/zing/zalo/ui/ChatActivity:yL	Lcom/zing/zalo/control/a;
    //   7: ifnull +41 -> 48
    //   10: aload_0
    //   11: getfield 12	com/zing/zalo/ui/dl:acV	Lcom/zing/zalo/ui/ChatActivity;
    //   14: getfield 27	com/zing/zalo/ui/ChatActivity:yL	Lcom/zing/zalo/control/a;
    //   17: invokevirtual 33	com/zing/zalo/control/a:fq	()Lcom/zing/zalo/control/m;
    //   20: invokevirtual 39	com/zing/zalo/control/m:fW	()Z
    //   23: ifeq +25 -> 48
    //   26: aload_0
    //   27: getfield 12	com/zing/zalo/ui/dl:acV	Lcom/zing/zalo/ui/ChatActivity;
    //   30: getfield 43	com/zing/zalo/ui/ChatActivity:KH	Landroid/content/res/Resources;
    //   33: ldc 44
    //   35: invokevirtual 50	android/content/res/Resources:getString	(I)Ljava/lang/String;
    //   38: invokestatic 56	com/zing/zalo/utils/p:eK	(Ljava/lang/String;)V
    //   41: iconst_0
    //   42: ireturn
    //   43: astore_3
    //   44: aload_3
    //   45: invokevirtual 59	java/lang/Exception:printStackTrace	()V
    //   48: aload_2
    //   49: invokevirtual 65	android/view/MotionEvent:getAction	()I
    //   52: tableswitch	default:+28 -> 80, 0:+30->82, 1:+363->415, 2:+253->305
    //   81: ireturn
    //   82: aload_0
    //   83: getfield 12	com/zing/zalo/ui/dl:acV	Lcom/zing/zalo/ui/ChatActivity;
    //   86: invokestatic 68	com/zing/zalo/ui/ChatActivity:B	(Lcom/zing/zalo/ui/ChatActivity;)V
    //   89: invokestatic 71	com/zing/zalo/utils/p:ru	()Z
    //   92: ifeq -51 -> 41
    //   95: invokestatic 74	com/zing/zalo/utils/p:rw	()Z
    //   98: ifeq +190 -> 288
    //   101: aload_0
    //   102: getfield 12	com/zing/zalo/ui/dl:acV	Lcom/zing/zalo/ui/ChatActivity;
    //   105: iconst_1
    //   106: invokestatic 78	com/zing/zalo/utils/p:c	(Landroid/app/Activity;Z)V
    //   109: aload_0
    //   110: getfield 12	com/zing/zalo/ui/dl:acV	Lcom/zing/zalo/ui/ChatActivity;
    //   113: iconst_0
    //   114: invokestatic 82	com/zing/zalo/ui/ChatActivity:n	(Lcom/zing/zalo/ui/ChatActivity;Z)V
    //   117: aload_0
    //   118: getfield 12	com/zing/zalo/ui/dl:acV	Lcom/zing/zalo/ui/ChatActivity;
    //   121: invokestatic 86	com/zing/zalo/ui/ChatActivity:H	(Lcom/zing/zalo/ui/ChatActivity;)Landroid/widget/FrameLayout;
    //   124: iconst_0
    //   125: invokevirtual 92	android/widget/FrameLayout:setVisibility	(I)V
    //   128: aload_0
    //   129: getfield 12	com/zing/zalo/ui/dl:acV	Lcom/zing/zalo/ui/ChatActivity;
    //   132: invokestatic 96	com/zing/zalo/ui/ChatActivity:I	(Lcom/zing/zalo/ui/ChatActivity;)Lcom/zing/zalo/uicontrol/AnimImageView;
    //   135: ldc 97
    //   137: invokevirtual 102	com/zing/zalo/uicontrol/AnimImageView:setImageResource	(I)V
    //   140: aload_0
    //   141: getfield 12	com/zing/zalo/ui/dl:acV	Lcom/zing/zalo/ui/ChatActivity;
    //   144: invokestatic 96	com/zing/zalo/ui/ChatActivity:I	(Lcom/zing/zalo/ui/ChatActivity;)Lcom/zing/zalo/uicontrol/AnimImageView;
    //   147: iconst_4
    //   148: newarray int
    //   150: dup
    //   151: iconst_0
    //   152: ldc 97
    //   154: iastore
    //   155: dup
    //   156: iconst_1
    //   157: ldc 103
    //   159: iastore
    //   160: dup
    //   161: iconst_2
    //   162: ldc 104
    //   164: iastore
    //   165: dup
    //   166: iconst_3
    //   167: ldc 105
    //   169: iastore
    //   170: invokevirtual 109	com/zing/zalo/uicontrol/AnimImageView:setAnimArray	([I)V
    //   173: aload_0
    //   174: getfield 12	com/zing/zalo/ui/dl:acV	Lcom/zing/zalo/ui/ChatActivity;
    //   177: invokestatic 96	com/zing/zalo/ui/ChatActivity:I	(Lcom/zing/zalo/ui/ChatActivity;)Lcom/zing/zalo/uicontrol/AnimImageView;
    //   180: invokevirtual 112	com/zing/zalo/uicontrol/AnimImageView:pq	()V
    //   183: aload_0
    //   184: getfield 12	com/zing/zalo/ui/dl:acV	Lcom/zing/zalo/ui/ChatActivity;
    //   187: invokestatic 116	com/zing/zalo/ui/ChatActivity:J	(Lcom/zing/zalo/ui/ChatActivity;)Landroid/widget/Button;
    //   190: aload_0
    //   191: getfield 12	com/zing/zalo/ui/dl:acV	Lcom/zing/zalo/ui/ChatActivity;
    //   194: getfield 43	com/zing/zalo/ui/ChatActivity:KH	Landroid/content/res/Resources;
    //   197: ldc 117
    //   199: invokevirtual 50	android/content/res/Resources:getString	(I)Ljava/lang/String;
    //   202: invokevirtual 123	android/widget/Button:setText	(Ljava/lang/CharSequence;)V
    //   205: invokestatic 129	com/zing/zalo/f/m:dM	()Lcom/zing/zalo/f/m;
    //   208: invokevirtual 132	com/zing/zalo/f/m:dX	()V
    //   211: aload_0
    //   212: getfield 12	com/zing/zalo/ui/dl:acV	Lcom/zing/zalo/ui/ChatActivity;
    //   215: invokestatic 135	com/zing/zalo/ui/ChatActivity:K	(Lcom/zing/zalo/ui/ChatActivity;)V
    //   218: aload_0
    //   219: getfield 12	com/zing/zalo/ui/dl:acV	Lcom/zing/zalo/ui/ChatActivity;
    //   222: invokestatic 138	com/zing/zalo/ui/ChatActivity:L	(Lcom/zing/zalo/ui/ChatActivity;)Landroid/widget/Button;
    //   225: ldc 139
    //   227: invokevirtual 142	android/widget/Button:setBackgroundResource	(I)V
    //   230: aload_0
    //   231: getfield 12	com/zing/zalo/ui/dl:acV	Lcom/zing/zalo/ui/ChatActivity;
    //   234: invokestatic 138	com/zing/zalo/ui/ChatActivity:L	(Lcom/zing/zalo/ui/ChatActivity;)Landroid/widget/Button;
    //   237: ldc 143
    //   239: invokevirtual 145	android/widget/Button:setText	(I)V
    //   242: aload_0
    //   243: getfield 12	com/zing/zalo/ui/dl:acV	Lcom/zing/zalo/ui/ChatActivity;
    //   246: invokestatic 149	com/zing/zalo/ui/ChatActivity:M	(Lcom/zing/zalo/ui/ChatActivity;)Landroid/widget/TextView;
    //   249: aload_0
    //   250: getfield 12	com/zing/zalo/ui/dl:acV	Lcom/zing/zalo/ui/ChatActivity;
    //   253: getfield 43	com/zing/zalo/ui/ChatActivity:KH	Landroid/content/res/Resources;
    //   256: ldc 150
    //   258: invokevirtual 50	android/content/res/Resources:getString	(I)Ljava/lang/String;
    //   261: invokevirtual 153	android/widget/TextView:setText	(Ljava/lang/CharSequence;)V
    //   264: aload_0
    //   265: getfield 12	com/zing/zalo/ui/dl:acV	Lcom/zing/zalo/ui/ChatActivity;
    //   268: invokestatic 157	com/zing/zalo/ui/ChatActivity:d	(Lcom/zing/zalo/ui/ChatActivity;)Landroid/os/Handler;
    //   271: new 159	com/zing/zalo/ui/dm
    //   274: dup
    //   275: aload_0
    //   276: invokespecial 162	com/zing/zalo/ui/dm:<init>	(Lcom/zing/zalo/ui/dl;)V
    //   279: ldc2_w 163
    //   282: invokevirtual 170	android/os/Handler:postDelayed	(Ljava/lang/Runnable;J)Z
    //   285: pop
    //   286: iconst_0
    //   287: ireturn
    //   288: aload_0
    //   289: getfield 12	com/zing/zalo/ui/dl:acV	Lcom/zing/zalo/ui/ChatActivity;
    //   292: getfield 43	com/zing/zalo/ui/ChatActivity:KH	Landroid/content/res/Resources;
    //   295: ldc 171
    //   297: invokevirtual 50	android/content/res/Resources:getString	(I)Ljava/lang/String;
    //   300: invokestatic 56	com/zing/zalo/utils/p:eK	(Ljava/lang/String;)V
    //   303: iconst_0
    //   304: ireturn
    //   305: aload_0
    //   306: getfield 12	com/zing/zalo/ui/dl:acV	Lcom/zing/zalo/ui/ChatActivity;
    //   309: invokestatic 175	com/zing/zalo/ui/ChatActivity:N	(Lcom/zing/zalo/ui/ChatActivity;)Landroid/graphics/Rect;
    //   312: ifnull -271 -> 41
    //   315: aload_0
    //   316: getfield 12	com/zing/zalo/ui/dl:acV	Lcom/zing/zalo/ui/ChatActivity;
    //   319: invokestatic 175	com/zing/zalo/ui/ChatActivity:N	(Lcom/zing/zalo/ui/ChatActivity;)Landroid/graphics/Rect;
    //   322: aload_2
    //   323: invokevirtual 179	android/view/MotionEvent:getRawX	()F
    //   326: f2i
    //   327: aload_2
    //   328: invokevirtual 182	android/view/MotionEvent:getRawY	()F
    //   331: f2i
    //   332: invokevirtual 188	android/graphics/Rect:contains	(II)Z
    //   335: ifeq +46 -> 381
    //   338: aload_0
    //   339: getfield 12	com/zing/zalo/ui/dl:acV	Lcom/zing/zalo/ui/ChatActivity;
    //   342: invokestatic 138	com/zing/zalo/ui/ChatActivity:L	(Lcom/zing/zalo/ui/ChatActivity;)Landroid/widget/Button;
    //   345: ldc 189
    //   347: invokevirtual 145	android/widget/Button:setText	(I)V
    //   350: aload_0
    //   351: getfield 12	com/zing/zalo/ui/dl:acV	Lcom/zing/zalo/ui/ChatActivity;
    //   354: invokestatic 138	com/zing/zalo/ui/ChatActivity:L	(Lcom/zing/zalo/ui/ChatActivity;)Landroid/widget/Button;
    //   357: ldc 190
    //   359: invokevirtual 142	android/widget/Button:setBackgroundResource	(I)V
    //   362: aload_0
    //   363: getfield 12	com/zing/zalo/ui/dl:acV	Lcom/zing/zalo/ui/ChatActivity;
    //   366: iconst_1
    //   367: invokestatic 82	com/zing/zalo/ui/ChatActivity:n	(Lcom/zing/zalo/ui/ChatActivity;Z)V
    //   370: iconst_0
    //   371: ireturn
    //   372: astore 5
    //   374: aload 5
    //   376: invokevirtual 59	java/lang/Exception:printStackTrace	()V
    //   379: iconst_0
    //   380: ireturn
    //   381: aload_0
    //   382: getfield 12	com/zing/zalo/ui/dl:acV	Lcom/zing/zalo/ui/ChatActivity;
    //   385: invokestatic 138	com/zing/zalo/ui/ChatActivity:L	(Lcom/zing/zalo/ui/ChatActivity;)Landroid/widget/Button;
    //   388: ldc 143
    //   390: invokevirtual 145	android/widget/Button:setText	(I)V
    //   393: aload_0
    //   394: getfield 12	com/zing/zalo/ui/dl:acV	Lcom/zing/zalo/ui/ChatActivity;
    //   397: invokestatic 138	com/zing/zalo/ui/ChatActivity:L	(Lcom/zing/zalo/ui/ChatActivity;)Landroid/widget/Button;
    //   400: ldc 139
    //   402: invokevirtual 142	android/widget/Button:setBackgroundResource	(I)V
    //   405: aload_0
    //   406: getfield 12	com/zing/zalo/ui/dl:acV	Lcom/zing/zalo/ui/ChatActivity;
    //   409: iconst_0
    //   410: invokestatic 82	com/zing/zalo/ui/ChatActivity:n	(Lcom/zing/zalo/ui/ChatActivity;Z)V
    //   413: iconst_0
    //   414: ireturn
    //   415: aload_0
    //   416: getfield 12	com/zing/zalo/ui/dl:acV	Lcom/zing/zalo/ui/ChatActivity;
    //   419: invokestatic 68	com/zing/zalo/ui/ChatActivity:B	(Lcom/zing/zalo/ui/ChatActivity;)V
    //   422: aload_0
    //   423: getfield 12	com/zing/zalo/ui/dl:acV	Lcom/zing/zalo/ui/ChatActivity;
    //   426: iconst_0
    //   427: invokestatic 78	com/zing/zalo/utils/p:c	(Landroid/app/Activity;Z)V
    //   430: aload_0
    //   431: getfield 12	com/zing/zalo/ui/dl:acV	Lcom/zing/zalo/ui/ChatActivity;
    //   434: invokestatic 138	com/zing/zalo/ui/ChatActivity:L	(Lcom/zing/zalo/ui/ChatActivity;)Landroid/widget/Button;
    //   437: ldc 139
    //   439: invokevirtual 142	android/widget/Button:setBackgroundResource	(I)V
    //   442: aload_0
    //   443: getfield 12	com/zing/zalo/ui/dl:acV	Lcom/zing/zalo/ui/ChatActivity;
    //   446: invokestatic 86	com/zing/zalo/ui/ChatActivity:H	(Lcom/zing/zalo/ui/ChatActivity;)Landroid/widget/FrameLayout;
    //   449: bipush 8
    //   451: invokevirtual 92	android/widget/FrameLayout:setVisibility	(I)V
    //   454: aload_0
    //   455: getfield 12	com/zing/zalo/ui/dl:acV	Lcom/zing/zalo/ui/ChatActivity;
    //   458: invokestatic 116	com/zing/zalo/ui/ChatActivity:J	(Lcom/zing/zalo/ui/ChatActivity;)Landroid/widget/Button;
    //   461: aload_0
    //   462: getfield 12	com/zing/zalo/ui/dl:acV	Lcom/zing/zalo/ui/ChatActivity;
    //   465: getfield 43	com/zing/zalo/ui/ChatActivity:KH	Landroid/content/res/Resources;
    //   468: ldc 191
    //   470: invokevirtual 50	android/content/res/Resources:getString	(I)Ljava/lang/String;
    //   473: invokevirtual 123	android/widget/Button:setText	(Ljava/lang/CharSequence;)V
    //   476: aload_0
    //   477: getfield 12	com/zing/zalo/ui/dl:acV	Lcom/zing/zalo/ui/ChatActivity;
    //   480: invokestatic 96	com/zing/zalo/ui/ChatActivity:I	(Lcom/zing/zalo/ui/ChatActivity;)Lcom/zing/zalo/uicontrol/AnimImageView;
    //   483: invokevirtual 194	com/zing/zalo/uicontrol/AnimImageView:pr	()V
    //   486: aload_0
    //   487: getfield 12	com/zing/zalo/ui/dl:acV	Lcom/zing/zalo/ui/ChatActivity;
    //   490: invokestatic 197	com/zing/zalo/ui/ChatActivity:O	(Lcom/zing/zalo/ui/ChatActivity;)V
    //   493: aload_0
    //   494: getfield 12	com/zing/zalo/ui/dl:acV	Lcom/zing/zalo/ui/ChatActivity;
    //   497: invokestatic 201	com/zing/zalo/ui/ChatActivity:P	(Lcom/zing/zalo/ui/ChatActivity;)Z
    //   500: ifne -459 -> 41
    //   503: aload_0
    //   504: getfield 12	com/zing/zalo/ui/dl:acV	Lcom/zing/zalo/ui/ChatActivity;
    //   507: invokestatic 205	com/zing/zalo/ui/ChatActivity:Q	(Lcom/zing/zalo/ui/ChatActivity;)Ljava/lang/String;
    //   510: ldc 207
    //   512: invokevirtual 213	java/lang/String:equals	(Ljava/lang/Object;)Z
    //   515: ifne -474 -> 41
    //   518: aload_0
    //   519: getfield 12	com/zing/zalo/ui/dl:acV	Lcom/zing/zalo/ui/ChatActivity;
    //   522: invokestatic 216	com/zing/zalo/ui/ChatActivity:R	(Lcom/zing/zalo/ui/ChatActivity;)Landroid/widget/Button;
    //   525: iconst_0
    //   526: invokevirtual 220	android/widget/Button:setEnabled	(Z)V
    //   529: aload_0
    //   530: getfield 12	com/zing/zalo/ui/dl:acV	Lcom/zing/zalo/ui/ChatActivity;
    //   533: invokestatic 149	com/zing/zalo/ui/ChatActivity:M	(Lcom/zing/zalo/ui/ChatActivity;)Landroid/widget/TextView;
    //   536: aload_0
    //   537: getfield 12	com/zing/zalo/ui/dl:acV	Lcom/zing/zalo/ui/ChatActivity;
    //   540: getfield 43	com/zing/zalo/ui/ChatActivity:KH	Landroid/content/res/Resources;
    //   543: ldc 150
    //   545: invokevirtual 50	android/content/res/Resources:getString	(I)Ljava/lang/String;
    //   548: invokevirtual 153	android/widget/TextView:setText	(Ljava/lang/CharSequence;)V
    //   551: invokestatic 129	com/zing/zalo/f/m:dM	()Lcom/zing/zalo/f/m;
    //   554: aload_0
    //   555: getfield 12	com/zing/zalo/ui/dl:acV	Lcom/zing/zalo/ui/ChatActivity;
    //   558: invokestatic 205	com/zing/zalo/ui/ChatActivity:Q	(Lcom/zing/zalo/ui/ChatActivity;)Ljava/lang/String;
    //   561: invokevirtual 224	com/zing/zalo/f/m:aC	(Ljava/lang/String;)I
    //   564: sipush 1000
    //   567: if_icmpge +20 -> 587
    //   570: aload_0
    //   571: getfield 12	com/zing/zalo/ui/dl:acV	Lcom/zing/zalo/ui/ChatActivity;
    //   574: getfield 43	com/zing/zalo/ui/ChatActivity:KH	Landroid/content/res/Resources;
    //   577: ldc 225
    //   579: invokevirtual 50	android/content/res/Resources:getString	(I)Ljava/lang/String;
    //   582: invokestatic 56	com/zing/zalo/utils/p:eK	(Ljava/lang/String;)V
    //   585: iconst_0
    //   586: ireturn
    //   587: aload_0
    //   588: getfield 12	com/zing/zalo/ui/dl:acV	Lcom/zing/zalo/ui/ChatActivity;
    //   591: aload_0
    //   592: getfield 12	com/zing/zalo/ui/dl:acV	Lcom/zing/zalo/ui/ChatActivity;
    //   595: invokestatic 205	com/zing/zalo/ui/ChatActivity:Q	(Lcom/zing/zalo/ui/ChatActivity;)Ljava/lang/String;
    //   598: invokestatic 228	com/zing/zalo/ui/ChatActivity:c	(Lcom/zing/zalo/ui/ChatActivity;Ljava/lang/String;)V
    //   601: iconst_0
    //   602: ireturn
    //   603: astore 6
    //   605: iconst_0
    //   606: ireturn
    //   607: astore 4
    //   609: iconst_0
    //   610: ireturn
    //
    // Exception table:
    //   from	to	target	type
    //   0	41	43	java/lang/Exception
    //   305	370	372	java/lang/Exception
    //   381	413	372	java/lang/Exception
    //   82	286	603	java/lang/Exception
    //   288	303	603	java/lang/Exception
    //   415	585	607	java/lang/Exception
    //   587	601	607	java/lang/Exception
  }
}

/* Location:           /home/danghvu/0day/Zalo/Zalo_1.0.8_dex2jar.jar
 * Qualified Name:     com.zing.zalo.ui.dl
 * JD-Core Version:    0.6.2
 */