package unk.com.zing.zalo.ui;

class fe
  implements Runnable
{
  fe(ChatActivity paramChatActivity, String paramString1, String paramString2, int paramInt)
  {
  }

  // ERROR //
  public void run()
  {
    // Byte code:
    //   0: getstatic 34	com/zing/zalo/g/a:CW	Ljava/lang/String;
    //   3: invokestatic 40	java/lang/Long:parseLong	(Ljava/lang/String;)J
    //   6: lstore 14
    //   8: lload 14
    //   10: lstore_2
    //   11: aload_0
    //   12: getfield 17	com/zing/zalo/ui/fe:acV	Lcom/zing/zalo/ui/ChatActivity;
    //   15: getfield 46	com/zing/zalo/ui/ChatActivity:yL	Lcom/zing/zalo/control/a;
    //   18: invokevirtual 52	com/zing/zalo/control/a:fq	()Lcom/zing/zalo/control/m;
    //   21: getfield 57	com/zing/zalo/control/m:xU	Ljava/lang/String;
    //   24: astore 17
    //   26: aload 17
    //   28: ldc 59
    //   30: invokevirtual 65	java/lang/String:startsWith	(Ljava/lang/String;)Z
    //   33: ifeq +28 -> 61
    //   36: aload 17
    //   38: ldc 59
    //   40: invokevirtual 69	java/lang/String:length	()I
    //   43: invokevirtual 73	java/lang/String:substring	(I)Ljava/lang/String;
    //   46: invokestatic 40	java/lang/Long:parseLong	(Ljava/lang/String;)J
    //   49: lstore 22
    //   51: lload_2
    //   52: lstore 4
    //   54: lload 22
    //   56: lstore 6
    //   58: goto +350 -> 408
    //   61: aload 17
    //   63: ldc 75
    //   65: invokevirtual 65	java/lang/String:startsWith	(Ljava/lang/String;)Z
    //   68: ifeq +28 -> 96
    //   71: aload 17
    //   73: ldc 75
    //   75: invokevirtual 69	java/lang/String:length	()I
    //   78: invokevirtual 73	java/lang/String:substring	(I)Ljava/lang/String;
    //   81: invokestatic 40	java/lang/Long:parseLong	(Ljava/lang/String;)J
    //   84: lstore 20
    //   86: lload_2
    //   87: lstore 4
    //   89: lload 20
    //   91: lstore 6
    //   93: goto +315 -> 408
    //   96: aload 17
    //   98: invokestatic 40	java/lang/Long:parseLong	(Ljava/lang/String;)J
    //   101: lstore 18
    //   103: lload_2
    //   104: lstore 4
    //   106: lload 18
    //   108: lstore 6
    //   110: goto +298 -> 408
    //   113: astore_1
    //   114: lconst_0
    //   115: lstore_2
    //   116: lload_2
    //   117: lstore 4
    //   119: lconst_0
    //   120: lstore 6
    //   122: goto +286 -> 408
    //   125: aload_0
    //   126: getfield 19	com/zing/zalo/ui/fe:adc	Ljava/lang/String;
    //   129: invokestatic 81	com/zing/zalo/utils/p:eJ	(Ljava/lang/String;)Ljava/lang/String;
    //   132: invokevirtual 85	java/lang/String:toLowerCase	()Ljava/lang/String;
    //   135: astore 9
    //   137: iconst_0
    //   138: istore 10
    //   140: iload 10
    //   142: getstatic 89	com/zing/zalo/g/a:BR	[Ljava/lang/String;
    //   145: arraylength
    //   146: if_icmplt +35 -> 181
    //   149: iconst_0
    //   150: istore 11
    //   152: iload 11
    //   154: ifne +47 -> 201
    //   157: aload_0
    //   158: getfield 17	com/zing/zalo/ui/fe:acV	Lcom/zing/zalo/ui/ChatActivity;
    //   161: getfield 93	com/zing/zalo/ui/ChatActivity:KH	Landroid/content/res/Resources;
    //   164: ldc 94
    //   166: invokevirtual 99	android/content/res/Resources:getString	(I)Ljava/lang/String;
    //   169: invokestatic 103	com/zing/zalo/utils/p:eK	(Ljava/lang/String;)V
    //   172: return
    //   173: astore 8
    //   175: aload 8
    //   177: invokevirtual 106	java/lang/Exception:printStackTrace	()V
    //   180: return
    //   181: aload 9
    //   183: getstatic 89	com/zing/zalo/g/a:BR	[Ljava/lang/String;
    //   186: iload 10
    //   188: aaload
    //   189: invokevirtual 110	java/lang/String:contains	(Ljava/lang/CharSequence;)Z
    //   192: ifeq +231 -> 423
    //   195: iconst_1
    //   196: istore 11
    //   198: goto -46 -> 152
    //   201: new 112	com/zing/zalo/control/b
    //   204: dup
    //   205: aload_0
    //   206: getfield 19	com/zing/zalo/ui/fe:adc	Ljava/lang/String;
    //   209: aload_0
    //   210: getfield 17	com/zing/zalo/ui/fe:acV	Lcom/zing/zalo/ui/ChatActivity;
    //   213: getfield 46	com/zing/zalo/ui/ChatActivity:yL	Lcom/zing/zalo/control/a;
    //   216: invokevirtual 52	com/zing/zalo/control/a:fq	()Lcom/zing/zalo/control/m;
    //   219: getfield 57	com/zing/zalo/control/m:xU	Ljava/lang/String;
    //   222: bipush 6
    //   224: invokespecial 115	com/zing/zalo/control/b:<init>	(Ljava/lang/String;Ljava/lang/String;I)V
    //   227: astore 12
    //   229: aload 12
    //   231: aload_0
    //   232: getfield 19	com/zing/zalo/ui/fe:adc	Ljava/lang/String;
    //   235: invokevirtual 118	com/zing/zalo/control/b:aK	(Ljava/lang/String;)V
    //   238: aload 12
    //   240: bipush 6
    //   242: invokevirtual 122	com/zing/zalo/control/b:setState	(I)V
    //   245: aload 12
    //   247: aload_0
    //   248: getfield 17	com/zing/zalo/ui/fe:acV	Lcom/zing/zalo/ui/ChatActivity;
    //   251: getfield 46	com/zing/zalo/ui/ChatActivity:yL	Lcom/zing/zalo/control/a;
    //   254: invokevirtual 52	com/zing/zalo/control/a:fq	()Lcom/zing/zalo/control/m;
    //   257: getfield 57	com/zing/zalo/control/m:xU	Ljava/lang/String;
    //   260: putfield 125	com/zing/zalo/control/b:wL	Ljava/lang/String;
    //   263: aload_0
    //   264: getfield 17	com/zing/zalo/ui/fe:acV	Lcom/zing/zalo/ui/ChatActivity;
    //   267: getfield 46	com/zing/zalo/ui/ChatActivity:yL	Lcom/zing/zalo/control/a;
    //   270: invokevirtual 52	com/zing/zalo/control/a:fq	()Lcom/zing/zalo/control/m;
    //   273: getfield 57	com/zing/zalo/control/m:xU	Ljava/lang/String;
    //   276: iconst_1
    //   277: invokestatic 131	com/zing/zalo/db/a:c	(Ljava/lang/String;Z)V
    //   280: aload 12
    //   282: new 133	com/zing/zalo/control/ac
    //   285: dup
    //   286: aload 12
    //   288: getfield 137	com/zing/zalo/control/b:timestamp	J
    //   291: ldc 139
    //   293: ldc 139
    //   295: aload_0
    //   296: getfield 21	com/zing/zalo/ui/fe:add	Ljava/lang/String;
    //   299: aload_0
    //   300: getfield 19	com/zing/zalo/ui/fe:adc	Ljava/lang/String;
    //   303: aload_0
    //   304: getfield 23	com/zing/zalo/ui/fe:ade	I
    //   307: aload_0
    //   308: getfield 23	com/zing/zalo/ui/fe:ade	I
    //   311: bipush 11
    //   313: invokespecial 142	com/zing/zalo/control/ac:<init>	(JLjava/lang/String;Ljava/lang/String;Ljava/lang/String;Ljava/lang/String;III)V
    //   316: invokevirtual 146	com/zing/zalo/control/b:a	(Lcom/zing/zalo/control/ac;)V
    //   319: invokestatic 152	com/zing/zalo/control/n:fX	()Lcom/zing/zalo/control/n;
    //   322: invokevirtual 156	com/zing/zalo/control/n:fZ	()Lcom/zing/zalo/control/i;
    //   325: invokeinterface 162 1 0
    //   330: aload 12
    //   332: invokevirtual 165	com/zing/zalo/control/a:c	(Lcom/zing/zalo/control/b;)V
    //   335: aload_0
    //   336: getfield 17	com/zing/zalo/ui/fe:acV	Lcom/zing/zalo/ui/ChatActivity;
    //   339: getfield 46	com/zing/zalo/ui/ChatActivity:yL	Lcom/zing/zalo/control/a;
    //   342: invokevirtual 52	com/zing/zalo/control/a:fq	()Lcom/zing/zalo/control/m;
    //   345: astore 13
    //   347: aload 13
    //   349: aload 12
    //   351: getfield 168	com/zing/zalo/control/b:state	I
    //   354: putfield 171	com/zing/zalo/control/m:yp	I
    //   357: aload 13
    //   359: aload 12
    //   361: getfield 137	com/zing/zalo/control/b:timestamp	J
    //   364: putfield 172	com/zing/zalo/control/m:timestamp	J
    //   367: invokestatic 176	com/zing/zalo/db/a:hn	()Lcom/zing/zalo/db/a;
    //   370: aload 12
    //   372: invokevirtual 179	com/zing/zalo/db/a:q	(Lcom/zing/zalo/control/b;)V
    //   375: invokestatic 176	com/zing/zalo/db/a:hn	()Lcom/zing/zalo/db/a;
    //   378: aload 13
    //   380: iconst_1
    //   381: aload 12
    //   383: getfield 182	com/zing/zalo/control/b:message	Ljava/lang/String;
    //   386: iconst_0
    //   387: aload 12
    //   389: getfield 185	com/zing/zalo/control/b:type	I
    //   392: invokevirtual 188	com/zing/zalo/db/a:a	(Lcom/zing/zalo/control/m;ZLjava/lang/String;II)V
    //   395: aload_0
    //   396: getfield 17	com/zing/zalo/ui/fe:acV	Lcom/zing/zalo/ui/ChatActivity;
    //   399: invokevirtual 191	com/zing/zalo/ui/ChatActivity:mK	()V
    //   402: return
    //   403: astore 16
    //   405: goto -289 -> 116
    //   408: lload 4
    //   410: lconst_0
    //   411: lcmp
    //   412: ifle +10 -> 422
    //   415: lload 6
    //   417: lconst_0
    //   418: lcmp
    //   419: ifgt -294 -> 125
    //   422: return
    //   423: iinc 10 1
    //   426: goto -286 -> 140
    //
    // Exception table:
    //   from	to	target	type
    //   0	8	113	java/lang/Exception
    //   125	137	173	java/lang/Exception
    //   140	149	173	java/lang/Exception
    //   157	172	173	java/lang/Exception
    //   181	195	173	java/lang/Exception
    //   201	402	173	java/lang/Exception
    //   11	51	403	java/lang/Exception
    //   61	86	403	java/lang/Exception
    //   96	103	403	java/lang/Exception
  }
}

/* Location:           /home/danghvu/0day/Zalo/Zalo_1.0.8_dex2jar.jar
 * Qualified Name:     com.zing.zalo.ui.fe
 * JD-Core Version:    0.6.2
 */