package unk.com.zing.zalo.ui;

import com.zing.zalo.k.f;

class hm
  implements f
{
  hm(hg paramhg)
  {
  }

  // ERROR //
  public void a(com.zing.zalo.k.d paramd, int paramInt1, int paramInt2)
  {
    // Byte code:
    //   0: iload_2
    //   1: ifne +97 -> 98
    //   4: invokestatic 25	com/zing/zalo/control/n:fX	()Lcom/zing/zalo/control/n;
    //   7: invokevirtual 29	com/zing/zalo/control/n:fZ	()Lcom/zing/zalo/control/i;
    //   10: invokeinterface 35 1 0
    //   15: invokevirtual 41	com/zing/zalo/control/a:fp	()Ljava/util/List;
    //   18: aload_0
    //   19: getfield 12	com/zing/zalo/ui/hm:adI	Lcom/zing/zalo/ui/hg;
    //   22: invokestatic 47	com/zing/zalo/ui/hg:g	(Lcom/zing/zalo/ui/hg;)I
    //   25: invokeinterface 53 2 0
    //   30: checkcast 55	com/zing/zalo/control/b
    //   33: invokevirtual 59	com/zing/zalo/control/b:fu	()Ljava/lang/String;
    //   36: astore 31
    //   38: new 61	android/os/Bundle
    //   41: dup
    //   42: invokespecial 62	android/os/Bundle:<init>	()V
    //   45: astore 32
    //   47: aload 32
    //   49: ldc 64
    //   51: aload 31
    //   53: invokevirtual 68	android/os/Bundle:putString	(Ljava/lang/String;Ljava/lang/String;)V
    //   56: new 70	android/content/Intent
    //   59: dup
    //   60: aload_0
    //   61: getfield 12	com/zing/zalo/ui/hm:adI	Lcom/zing/zalo/ui/hg;
    //   64: invokestatic 74	com/zing/zalo/ui/hg:q	(Lcom/zing/zalo/ui/hg;)Lcom/zing/zalo/ui/ChatActivity;
    //   67: ldc 76
    //   69: invokespecial 79	android/content/Intent:<init>	(Landroid/content/Context;Ljava/lang/Class;)V
    //   72: astore 33
    //   74: aload 33
    //   76: aload 32
    //   78: invokevirtual 83	android/content/Intent:putExtras	(Landroid/os/Bundle;)Landroid/content/Intent;
    //   81: pop
    //   82: aload_0
    //   83: getfield 12	com/zing/zalo/ui/hm:adI	Lcom/zing/zalo/ui/hg;
    //   86: invokestatic 74	com/zing/zalo/ui/hg:q	(Lcom/zing/zalo/ui/hg;)Lcom/zing/zalo/ui/ChatActivity;
    //   89: aload 33
    //   91: sipush 1004
    //   94: invokevirtual 89	com/zing/zalo/ui/ChatActivity:startActivityForResult	(Landroid/content/Intent;I)V
    //   97: return
    //   98: iload_2
    //   99: iconst_1
    //   100: if_icmpne +200 -> 300
    //   103: invokestatic 25	com/zing/zalo/control/n:fX	()Lcom/zing/zalo/control/n;
    //   106: invokevirtual 29	com/zing/zalo/control/n:fZ	()Lcom/zing/zalo/control/i;
    //   109: invokeinterface 35 1 0
    //   114: invokevirtual 41	com/zing/zalo/control/a:fp	()Ljava/util/List;
    //   117: astore 27
    //   119: aload 27
    //   121: aload_0
    //   122: getfield 12	com/zing/zalo/ui/hm:adI	Lcom/zing/zalo/ui/hg;
    //   125: invokestatic 47	com/zing/zalo/ui/hg:g	(Lcom/zing/zalo/ui/hg;)I
    //   128: invokeinterface 53 2 0
    //   133: checkcast 55	com/zing/zalo/control/b
    //   136: invokevirtual 93	com/zing/zalo/control/b:getType	()I
    //   139: iconst_1
    //   140: if_icmpeq +99 -> 239
    //   143: aload 27
    //   145: aload_0
    //   146: getfield 12	com/zing/zalo/ui/hm:adI	Lcom/zing/zalo/ui/hg;
    //   149: invokestatic 47	com/zing/zalo/ui/hg:g	(Lcom/zing/zalo/ui/hg;)I
    //   152: invokeinterface 53 2 0
    //   157: checkcast 55	com/zing/zalo/control/b
    //   160: invokevirtual 93	com/zing/zalo/control/b:getType	()I
    //   163: iconst_5
    //   164: if_icmpeq +75 -> 239
    //   167: aload 27
    //   169: aload_0
    //   170: getfield 12	com/zing/zalo/ui/hm:adI	Lcom/zing/zalo/ui/hg;
    //   173: invokestatic 47	com/zing/zalo/ui/hg:g	(Lcom/zing/zalo/ui/hg;)I
    //   176: invokeinterface 53 2 0
    //   181: checkcast 55	com/zing/zalo/control/b
    //   184: invokevirtual 93	com/zing/zalo/control/b:getType	()I
    //   187: iconst_2
    //   188: if_icmpeq +51 -> 239
    //   191: aload 27
    //   193: aload_0
    //   194: getfield 12	com/zing/zalo/ui/hm:adI	Lcom/zing/zalo/ui/hg;
    //   197: invokestatic 47	com/zing/zalo/ui/hg:g	(Lcom/zing/zalo/ui/hg;)I
    //   200: invokeinterface 53 2 0
    //   205: checkcast 55	com/zing/zalo/control/b
    //   208: invokevirtual 93	com/zing/zalo/control/b:getType	()I
    //   211: iconst_3
    //   212: if_icmpeq +27 -> 239
    //   215: aload 27
    //   217: aload_0
    //   218: getfield 12	com/zing/zalo/ui/hm:adI	Lcom/zing/zalo/ui/hg;
    //   221: invokestatic 47	com/zing/zalo/ui/hg:g	(Lcom/zing/zalo/ui/hg;)I
    //   224: invokeinterface 53 2 0
    //   229: checkcast 55	com/zing/zalo/control/b
    //   232: invokevirtual 93	com/zing/zalo/control/b:getType	()I
    //   235: iconst_4
    //   236: if_icmpne +35 -> 271
    //   239: aload 27
    //   241: aload_0
    //   242: getfield 12	com/zing/zalo/ui/hm:adI	Lcom/zing/zalo/ui/hg;
    //   245: invokestatic 47	com/zing/zalo/ui/hg:g	(Lcom/zing/zalo/ui/hg;)I
    //   248: invokeinterface 53 2 0
    //   253: checkcast 55	com/zing/zalo/control/b
    //   256: invokevirtual 59	com/zing/zalo/control/b:fu	()Ljava/lang/String;
    //   259: astore 28
    //   261: aload_0
    //   262: getfield 12	com/zing/zalo/ui/hm:adI	Lcom/zing/zalo/ui/hg;
    //   265: aload 28
    //   267: invokestatic 96	com/zing/zalo/ui/hg:a	(Lcom/zing/zalo/ui/hg;Ljava/lang/String;)V
    //   270: return
    //   271: aload 27
    //   273: aload_0
    //   274: getfield 12	com/zing/zalo/ui/hm:adI	Lcom/zing/zalo/ui/hg;
    //   277: invokestatic 47	com/zing/zalo/ui/hg:g	(Lcom/zing/zalo/ui/hg;)I
    //   280: invokeinterface 53 2 0
    //   285: checkcast 55	com/zing/zalo/control/b
    //   288: invokevirtual 99	com/zing/zalo/control/b:getMessage	()Ljava/lang/String;
    //   291: astore 29
    //   293: aload 29
    //   295: astore 28
    //   297: goto -36 -> 261
    //   300: iload_2
    //   301: iconst_2
    //   302: if_icmpne +502 -> 804
    //   305: invokestatic 25	com/zing/zalo/control/n:fX	()Lcom/zing/zalo/control/n;
    //   308: invokevirtual 29	com/zing/zalo/control/n:fZ	()Lcom/zing/zalo/control/i;
    //   311: astore 7
    //   313: aload 7
    //   315: invokeinterface 35 1 0
    //   320: invokevirtual 41	com/zing/zalo/control/a:fp	()Ljava/util/List;
    //   323: astore 8
    //   325: aload 7
    //   327: invokeinterface 35 1 0
    //   332: invokevirtual 103	com/zing/zalo/control/a:fq	()Lcom/zing/zalo/control/m;
    //   335: getfield 109	com/zing/zalo/control/m:xU	Ljava/lang/String;
    //   338: astore 9
    //   340: aload_0
    //   341: getfield 12	com/zing/zalo/ui/hm:adI	Lcom/zing/zalo/ui/hg;
    //   344: invokestatic 47	com/zing/zalo/ui/hg:g	(Lcom/zing/zalo/ui/hg;)I
    //   347: ifne +301 -> 648
    //   350: aload_0
    //   351: getfield 12	com/zing/zalo/ui/hm:adI	Lcom/zing/zalo/ui/hg;
    //   354: invokestatic 113	com/zing/zalo/ui/hg:e	(Lcom/zing/zalo/ui/hg;)Lcom/zing/zalo/a/m;
    //   357: invokevirtual 119	com/zing/zalo/a/m:cl	()Z
    //   360: ifeq +269 -> 629
    //   363: aload 7
    //   365: invokeinterface 35 1 0
    //   370: invokevirtual 103	com/zing/zalo/control/a:fq	()Lcom/zing/zalo/control/m;
    //   373: getfield 109	com/zing/zalo/control/m:xU	Ljava/lang/String;
    //   376: astore 19
    //   378: aload 8
    //   380: iconst_m1
    //   381: aload_0
    //   382: getfield 12	com/zing/zalo/ui/hm:adI	Lcom/zing/zalo/ui/hg;
    //   385: invokestatic 47	com/zing/zalo/ui/hg:g	(Lcom/zing/zalo/ui/hg;)I
    //   388: iadd
    //   389: invokeinterface 53 2 0
    //   394: checkcast 55	com/zing/zalo/control/b
    //   397: getfield 122	com/zing/zalo/control/b:message	Ljava/lang/String;
    //   400: astore 20
    //   402: aload 8
    //   404: iconst_m1
    //   405: aload_0
    //   406: getfield 12	com/zing/zalo/ui/hm:adI	Lcom/zing/zalo/ui/hg;
    //   409: invokestatic 47	com/zing/zalo/ui/hg:g	(Lcom/zing/zalo/ui/hg;)I
    //   412: iadd
    //   413: invokeinterface 53 2 0
    //   418: checkcast 55	com/zing/zalo/control/b
    //   421: invokevirtual 93	com/zing/zalo/control/b:getType	()I
    //   424: istore 21
    //   426: aload 8
    //   428: iconst_m1
    //   429: aload_0
    //   430: getfield 12	com/zing/zalo/ui/hm:adI	Lcom/zing/zalo/ui/hg;
    //   433: invokestatic 47	com/zing/zalo/ui/hg:g	(Lcom/zing/zalo/ui/hg;)I
    //   436: iadd
    //   437: invokeinterface 53 2 0
    //   442: checkcast 55	com/zing/zalo/control/b
    //   445: invokevirtual 125	com/zing/zalo/control/b:fx	()Z
    //   448: istore 22
    //   450: aload 8
    //   452: iconst_m1
    //   453: aload_0
    //   454: getfield 12	com/zing/zalo/ui/hm:adI	Lcom/zing/zalo/ui/hg;
    //   457: invokestatic 47	com/zing/zalo/ui/hg:g	(Lcom/zing/zalo/ui/hg;)I
    //   460: iadd
    //   461: invokeinterface 53 2 0
    //   466: checkcast 55	com/zing/zalo/control/b
    //   469: getfield 129	com/zing/zalo/control/b:wH	I
    //   472: istore 23
    //   474: aload 8
    //   476: iconst_m1
    //   477: aload_0
    //   478: getfield 12	com/zing/zalo/ui/hm:adI	Lcom/zing/zalo/ui/hg;
    //   481: invokestatic 47	com/zing/zalo/ui/hg:g	(Lcom/zing/zalo/ui/hg;)I
    //   484: iadd
    //   485: invokeinterface 53 2 0
    //   490: checkcast 55	com/zing/zalo/control/b
    //   493: getfield 133	com/zing/zalo/control/b:timestamp	J
    //   496: lstore 24
    //   498: invokestatic 139	com/zing/zalo/db/a:hn	()Lcom/zing/zalo/db/a;
    //   501: aload 19
    //   503: aload 20
    //   505: iload 22
    //   507: iload 21
    //   509: lload 24
    //   511: iload 23
    //   513: invokevirtual 142	com/zing/zalo/db/a:a	(Ljava/lang/String;Ljava/lang/String;ZIJI)V
    //   516: aload 8
    //   518: aload_0
    //   519: getfield 12	com/zing/zalo/ui/hm:adI	Lcom/zing/zalo/ui/hg;
    //   522: invokestatic 47	com/zing/zalo/ui/hg:g	(Lcom/zing/zalo/ui/hg;)I
    //   525: invokeinterface 145 2 0
    //   530: checkcast 55	com/zing/zalo/control/b
    //   533: astore 17
    //   535: invokestatic 139	com/zing/zalo/db/a:hn	()Lcom/zing/zalo/db/a;
    //   538: aload 17
    //   540: invokevirtual 149	com/zing/zalo/db/a:r	(Lcom/zing/zalo/control/b;)V
    //   543: aload 9
    //   545: invokestatic 155	com/zing/zalo/utils/p:eS	(Ljava/lang/String;)Z
    //   548: ifeq +60 -> 608
    //   551: invokestatic 139	com/zing/zalo/db/a:hn	()Lcom/zing/zalo/db/a;
    //   554: aload 9
    //   556: invokevirtual 158	com/zing/zalo/db/a:bp	(Ljava/lang/String;)Z
    //   559: ifne +49 -> 608
    //   562: aload 9
    //   564: ldc 160
    //   566: invokevirtual 166	java/lang/String:equals	(Ljava/lang/Object;)Z
    //   569: ifne +39 -> 608
    //   572: invokestatic 139	com/zing/zalo/db/a:hn	()Lcom/zing/zalo/db/a;
    //   575: aload 9
    //   577: invokevirtual 170	com/zing/zalo/db/a:by	(Ljava/lang/String;)Lcom/zing/zalo/control/m;
    //   580: astore 18
    //   582: aload 18
    //   584: ifnull +24 -> 608
    //   587: aload 18
    //   589: getfield 109	com/zing/zalo/control/m:xU	Ljava/lang/String;
    //   592: ldc 172
    //   594: invokevirtual 166	java/lang/String:equals	(Ljava/lang/Object;)Z
    //   597: ifne +11 -> 608
    //   600: invokestatic 139	com/zing/zalo/db/a:hn	()Lcom/zing/zalo/db/a;
    //   603: aload 18
    //   605: invokevirtual 175	com/zing/zalo/db/a:g	(Lcom/zing/zalo/control/m;)V
    //   608: aload_0
    //   609: getfield 12	com/zing/zalo/ui/hm:adI	Lcom/zing/zalo/ui/hg;
    //   612: invokestatic 113	com/zing/zalo/ui/hg:e	(Lcom/zing/zalo/ui/hg;)Lcom/zing/zalo/a/m;
    //   615: ifnull -518 -> 97
    //   618: aload_0
    //   619: getfield 12	com/zing/zalo/ui/hm:adI	Lcom/zing/zalo/ui/hg;
    //   622: invokestatic 113	com/zing/zalo/ui/hg:e	(Lcom/zing/zalo/ui/hg;)Lcom/zing/zalo/a/m;
    //   625: invokevirtual 178	com/zing/zalo/a/m:ck	()V
    //   628: return
    //   629: invokestatic 139	com/zing/zalo/db/a:hn	()Lcom/zing/zalo/db/a;
    //   632: aload 7
    //   634: invokeinterface 35 1 0
    //   639: invokevirtual 103	com/zing/zalo/control/a:fq	()Lcom/zing/zalo/control/m;
    //   642: invokevirtual 181	com/zing/zalo/db/a:i	(Lcom/zing/zalo/control/m;)V
    //   645: goto -129 -> 516
    //   648: aload 7
    //   650: invokeinterface 35 1 0
    //   655: invokevirtual 103	com/zing/zalo/control/a:fq	()Lcom/zing/zalo/control/m;
    //   658: getfield 109	com/zing/zalo/control/m:xU	Ljava/lang/String;
    //   661: astore 10
    //   663: aload 8
    //   665: iconst_m1
    //   666: aload_0
    //   667: getfield 12	com/zing/zalo/ui/hm:adI	Lcom/zing/zalo/ui/hg;
    //   670: invokestatic 47	com/zing/zalo/ui/hg:g	(Lcom/zing/zalo/ui/hg;)I
    //   673: iadd
    //   674: invokeinterface 53 2 0
    //   679: checkcast 55	com/zing/zalo/control/b
    //   682: getfield 122	com/zing/zalo/control/b:message	Ljava/lang/String;
    //   685: astore 11
    //   687: aload 8
    //   689: iconst_m1
    //   690: aload_0
    //   691: getfield 12	com/zing/zalo/ui/hm:adI	Lcom/zing/zalo/ui/hg;
    //   694: invokestatic 47	com/zing/zalo/ui/hg:g	(Lcom/zing/zalo/ui/hg;)I
    //   697: iadd
    //   698: invokeinterface 53 2 0
    //   703: checkcast 55	com/zing/zalo/control/b
    //   706: invokevirtual 93	com/zing/zalo/control/b:getType	()I
    //   709: istore 12
    //   711: aload 8
    //   713: iconst_m1
    //   714: aload_0
    //   715: getfield 12	com/zing/zalo/ui/hm:adI	Lcom/zing/zalo/ui/hg;
    //   718: invokestatic 47	com/zing/zalo/ui/hg:g	(Lcom/zing/zalo/ui/hg;)I
    //   721: iadd
    //   722: invokeinterface 53 2 0
    //   727: checkcast 55	com/zing/zalo/control/b
    //   730: invokevirtual 125	com/zing/zalo/control/b:fx	()Z
    //   733: istore 13
    //   735: aload 8
    //   737: iconst_m1
    //   738: aload_0
    //   739: getfield 12	com/zing/zalo/ui/hm:adI	Lcom/zing/zalo/ui/hg;
    //   742: invokestatic 47	com/zing/zalo/ui/hg:g	(Lcom/zing/zalo/ui/hg;)I
    //   745: iadd
    //   746: invokeinterface 53 2 0
    //   751: checkcast 55	com/zing/zalo/control/b
    //   754: getfield 129	com/zing/zalo/control/b:wH	I
    //   757: istore 14
    //   759: aload 8
    //   761: iconst_m1
    //   762: aload_0
    //   763: getfield 12	com/zing/zalo/ui/hm:adI	Lcom/zing/zalo/ui/hg;
    //   766: invokestatic 47	com/zing/zalo/ui/hg:g	(Lcom/zing/zalo/ui/hg;)I
    //   769: iadd
    //   770: invokeinterface 53 2 0
    //   775: checkcast 55	com/zing/zalo/control/b
    //   778: getfield 133	com/zing/zalo/control/b:timestamp	J
    //   781: lstore 15
    //   783: invokestatic 139	com/zing/zalo/db/a:hn	()Lcom/zing/zalo/db/a;
    //   786: aload 10
    //   788: aload 11
    //   790: iload 13
    //   792: iload 12
    //   794: lload 15
    //   796: iload 14
    //   798: invokevirtual 142	com/zing/zalo/db/a:a	(Ljava/lang/String;Ljava/lang/String;ZIJI)V
    //   801: goto -285 -> 516
    //   804: iload_2
    //   805: iconst_3
    //   806: if_icmpne -709 -> 97
    //   809: invokestatic 25	com/zing/zalo/control/n:fX	()Lcom/zing/zalo/control/n;
    //   812: invokevirtual 29	com/zing/zalo/control/n:fZ	()Lcom/zing/zalo/control/i;
    //   815: invokeinterface 35 1 0
    //   820: invokevirtual 41	com/zing/zalo/control/a:fp	()Ljava/util/List;
    //   823: aload_0
    //   824: getfield 12	com/zing/zalo/ui/hm:adI	Lcom/zing/zalo/ui/hg;
    //   827: invokestatic 47	com/zing/zalo/ui/hg:g	(Lcom/zing/zalo/ui/hg;)I
    //   830: invokeinterface 53 2 0
    //   835: checkcast 55	com/zing/zalo/control/b
    //   838: invokevirtual 59	com/zing/zalo/control/b:fu	()Ljava/lang/String;
    //   841: astore 5
    //   843: aload 5
    //   845: ldc 172
    //   847: invokevirtual 166	java/lang/String:equals	(Ljava/lang/Object;)Z
    //   850: ifne -753 -> 97
    //   853: aload_0
    //   854: getfield 12	com/zing/zalo/ui/hm:adI	Lcom/zing/zalo/ui/hg;
    //   857: invokestatic 74	com/zing/zalo/ui/hg:q	(Lcom/zing/zalo/ui/hg;)Lcom/zing/zalo/ui/ChatActivity;
    //   860: aload 5
    //   862: invokestatic 184	com/zing/zalo/ui/ChatActivity:a	(Lcom/zing/zalo/ui/ChatActivity;Ljava/lang/String;)V
    //   865: return
    //   866: astore 4
    //   868: return
    //   869: astore 30
    //   871: return
    //   872: astore 26
    //   874: return
    //   875: astore 6
    //   877: return
    //
    // Exception table:
    //   from	to	target	type
    //   809	865	866	java/lang/Exception
    //   4	97	869	java/lang/Exception
    //   103	239	872	java/lang/Exception
    //   239	261	872	java/lang/Exception
    //   261	270	872	java/lang/Exception
    //   271	293	872	java/lang/Exception
    //   305	516	875	java/lang/Exception
    //   516	582	875	java/lang/Exception
    //   587	608	875	java/lang/Exception
    //   608	628	875	java/lang/Exception
    //   629	645	875	java/lang/Exception
    //   648	801	875	java/lang/Exception
  }
}

/* Location:           /home/danghvu/0day/Zalo/Zalo_1.0.8_dex2jar.jar
 * Qualified Name:     com.zing.zalo.ui.hm
 * JD-Core Version:    0.6.2
 */