package unk.com.zing.zalo.ui;

import android.view.View.OnClickListener;

class hq
  implements View.OnClickListener
{
  hq(hg paramhg)
  {
  }

  // ERROR //
  public void onClick(android.view.View paramView)
  {
    // Byte code:
    //   0: aload_0
    //   1: getfield 12	com/zing/zalo/ui/hq:adI	Lcom/zing/zalo/ui/hg;
    //   4: invokestatic 25	com/zing/zalo/ui/hg:q	(Lcom/zing/zalo/ui/hg;)Lcom/zing/zalo/ui/ChatActivity;
    //   7: getfield 31	com/zing/zalo/ui/ChatActivity:yL	Lcom/zing/zalo/control/a;
    //   10: ifnull +49 -> 59
    //   13: aload_0
    //   14: getfield 12	com/zing/zalo/ui/hq:adI	Lcom/zing/zalo/ui/hg;
    //   17: invokestatic 25	com/zing/zalo/ui/hg:q	(Lcom/zing/zalo/ui/hg;)Lcom/zing/zalo/ui/ChatActivity;
    //   20: getfield 31	com/zing/zalo/ui/ChatActivity:yL	Lcom/zing/zalo/control/a;
    //   23: invokevirtual 37	com/zing/zalo/control/a:fq	()Lcom/zing/zalo/control/m;
    //   26: ifnull +33 -> 59
    //   29: aload_0
    //   30: getfield 12	com/zing/zalo/ui/hq:adI	Lcom/zing/zalo/ui/hg;
    //   33: invokestatic 25	com/zing/zalo/ui/hg:q	(Lcom/zing/zalo/ui/hg;)Lcom/zing/zalo/ui/ChatActivity;
    //   36: getfield 31	com/zing/zalo/ui/ChatActivity:yL	Lcom/zing/zalo/control/a;
    //   39: invokevirtual 37	com/zing/zalo/control/a:fq	()Lcom/zing/zalo/control/m;
    //   42: invokevirtual 43	com/zing/zalo/control/m:fW	()Z
    //   45: ifeq +14 -> 59
    //   48: aload_0
    //   49: getfield 12	com/zing/zalo/ui/hq:adI	Lcom/zing/zalo/ui/hg;
    //   52: invokestatic 25	com/zing/zalo/ui/hg:q	(Lcom/zing/zalo/ui/hg;)Lcom/zing/zalo/ui/ChatActivity;
    //   55: invokestatic 47	com/zing/zalo/ui/ChatActivity:h	(Lcom/zing/zalo/ui/ChatActivity;)V
    //   58: return
    //   59: aload_0
    //   60: getfield 12	com/zing/zalo/ui/hq:adI	Lcom/zing/zalo/ui/hg;
    //   63: invokestatic 25	com/zing/zalo/ui/hg:q	(Lcom/zing/zalo/ui/hg;)Lcom/zing/zalo/ui/ChatActivity;
    //   66: invokevirtual 50	com/zing/zalo/ui/ChatActivity:mR	()V
    //   69: aload_0
    //   70: getfield 12	com/zing/zalo/ui/hq:adI	Lcom/zing/zalo/ui/hg;
    //   73: invokestatic 25	com/zing/zalo/ui/hg:q	(Lcom/zing/zalo/ui/hg;)Lcom/zing/zalo/ui/ChatActivity;
    //   76: getfield 54	com/zing/zalo/ui/ChatActivity:Nk	Lcom/zing/zalo/uicontrol/CustomEditTextDrawable;
    //   79: ifnull +52 -> 131
    //   82: aload_0
    //   83: getfield 12	com/zing/zalo/ui/hq:adI	Lcom/zing/zalo/ui/hg;
    //   86: invokestatic 25	com/zing/zalo/ui/hg:q	(Lcom/zing/zalo/ui/hg;)Lcom/zing/zalo/ui/ChatActivity;
    //   89: getfield 54	com/zing/zalo/ui/ChatActivity:Nk	Lcom/zing/zalo/uicontrol/CustomEditTextDrawable;
    //   92: invokevirtual 60	com/zing/zalo/uicontrol/CustomEditTextDrawable:getText	()Landroid/text/Editable;
    //   95: invokeinterface 66 1 0
    //   100: astore 4
    //   102: aload_0
    //   103: getfield 12	com/zing/zalo/ui/hq:adI	Lcom/zing/zalo/ui/hg;
    //   106: invokestatic 25	com/zing/zalo/ui/hg:q	(Lcom/zing/zalo/ui/hg;)Lcom/zing/zalo/ui/ChatActivity;
    //   109: aload 4
    //   111: aload_0
    //   112: getfield 12	com/zing/zalo/ui/hq:adI	Lcom/zing/zalo/ui/hg;
    //   115: invokestatic 25	com/zing/zalo/ui/hg:q	(Lcom/zing/zalo/ui/hg;)Lcom/zing/zalo/ui/ChatActivity;
    //   118: getfield 31	com/zing/zalo/ui/ChatActivity:yL	Lcom/zing/zalo/control/a;
    //   121: invokevirtual 37	com/zing/zalo/control/a:fq	()Lcom/zing/zalo/control/m;
    //   124: getfield 70	com/zing/zalo/control/m:xU	Ljava/lang/String;
    //   127: iconst_1
    //   128: invokevirtual 74	com/zing/zalo/ui/ChatActivity:c	(Ljava/lang/String;Ljava/lang/String;Z)V
    //   131: aload_0
    //   132: getfield 12	com/zing/zalo/ui/hq:adI	Lcom/zing/zalo/ui/hg;
    //   135: invokestatic 25	com/zing/zalo/ui/hg:q	(Lcom/zing/zalo/ui/hg;)Lcom/zing/zalo/ui/ChatActivity;
    //   138: invokestatic 77	com/zing/zalo/ui/ChatActivity:i	(Lcom/zing/zalo/ui/ChatActivity;)V
    //   141: aload_0
    //   142: getfield 12	com/zing/zalo/ui/hq:adI	Lcom/zing/zalo/ui/hg;
    //   145: invokestatic 25	com/zing/zalo/ui/hg:q	(Lcom/zing/zalo/ui/hg;)Lcom/zing/zalo/ui/ChatActivity;
    //   148: invokevirtual 80	com/zing/zalo/ui/ChatActivity:finish	()V
    //   151: return
    //   152: astore_2
    //   153: aload_2
    //   154: invokevirtual 83	java/lang/Exception:printStackTrace	()V
    //   157: return
    //   158: astore_3
    //   159: goto -18 -> 141
    //
    // Exception table:
    //   from	to	target	type
    //   0	58	152	java/lang/Exception
    //   59	69	152	java/lang/Exception
    //   141	151	152	java/lang/Exception
    //   69	131	158	java/lang/Exception
    //   131	141	158	java/lang/Exception
  }
}

/* Location:           /home/danghvu/0day/Zalo/Zalo_1.0.8_dex2jar.jar
 * Qualified Name:     com.zing.zalo.ui.hq
 * JD-Core Version:    0.6.2
 */