package unk.com.zing.zalo.ui;

class rh
  implements Runnable
{
  rh(ImageViewActivity paramImageViewActivity)
  {
  }

  // ERROR //
  public void run()
  {
    // Byte code:
    //   0: aload_0
    //   1: getfield 12	com/zing/zalo/ui/rh:ajd	Lcom/zing/zalo/ui/ImageViewActivity;
    //   4: invokestatic 31	com/zing/zalo/ui/ImageViewActivity:w	(Lcom/zing/zalo/ui/ImageViewActivity;)V
    //   7: aload_0
    //   8: getfield 12	com/zing/zalo/ui/rh:ajd	Lcom/zing/zalo/ui/ImageViewActivity;
    //   11: aload_0
    //   12: getfield 12	com/zing/zalo/ui/rh:ajd	Lcom/zing/zalo/ui/ImageViewActivity;
    //   15: invokestatic 35	com/zing/zalo/ui/ImageViewActivity:a	(Lcom/zing/zalo/ui/ImageViewActivity;)Lcom/zing/zalo/a/cl;
    //   18: invokevirtual 41	com/zing/zalo/a/cl:getPosition	()I
    //   21: invokestatic 44	com/zing/zalo/ui/ImageViewActivity:a	(Lcom/zing/zalo/ui/ImageViewActivity;I)V
    //   24: aload_0
    //   25: getfield 12	com/zing/zalo/ui/rh:ajd	Lcom/zing/zalo/ui/ImageViewActivity;
    //   28: getfield 48	com/zing/zalo/ui/ImageViewActivity:oO	Ljava/util/ArrayList;
    //   31: aload_0
    //   32: getfield 12	com/zing/zalo/ui/rh:ajd	Lcom/zing/zalo/ui/ImageViewActivity;
    //   35: invokestatic 52	com/zing/zalo/ui/ImageViewActivity:b	(Lcom/zing/zalo/ui/ImageViewActivity;)I
    //   38: invokevirtual 58	java/util/ArrayList:get	(I)Ljava/lang/Object;
    //   41: checkcast 60	com/zing/zalo/control/x
    //   44: getfield 64	com/zing/zalo/control/x:gh	Ljava/lang/String;
    //   47: astore_2
    //   48: aload_2
    //   49: ldc 66
    //   51: invokevirtual 72	java/lang/String:contains	(Ljava/lang/CharSequence;)Z
    //   54: ifeq +519 -> 573
    //   57: aload_0
    //   58: getfield 12	com/zing/zalo/ui/rh:ajd	Lcom/zing/zalo/ui/ImageViewActivity;
    //   61: invokestatic 76	com/zing/zalo/ui/ImageViewActivity:r	(Lcom/zing/zalo/ui/ImageViewActivity;)Lcom/a/a;
    //   64: aload_2
    //   65: invokevirtual 82	com/a/a:c	(Ljava/lang/String;)Ljava/io/File;
    //   68: invokevirtual 88	java/io/File:getAbsolutePath	()Ljava/lang/String;
    //   71: astore_3
    //   72: aload_3
    //   73: invokevirtual 91	java/lang/String:length	()I
    //   76: ifle +227 -> 303
    //   79: aconst_null
    //   80: astore 4
    //   82: bipush 10
    //   84: newarray char
    //   86: astore 5
    //   88: new 93	java/io/DataInputStream
    //   91: dup
    //   92: new 95	java/io/FileInputStream
    //   95: dup
    //   96: aload_3
    //   97: invokespecial 98	java/io/FileInputStream:<init>	(Ljava/lang/String;)V
    //   100: invokespecial 101	java/io/DataInputStream:<init>	(Ljava/io/InputStream;)V
    //   103: astore 6
    //   105: iconst_0
    //   106: istore 7
    //   108: iload 7
    //   110: bipush 10
    //   112: if_icmplt +192 -> 304
    //   115: aload 5
    //   117: invokestatic 105	java/lang/String:valueOf	([C)Ljava/lang/String;
    //   120: astore 31
    //   122: aload 6
    //   124: ifnull +520 -> 644
    //   127: aload 6
    //   129: invokevirtual 108	java/io/DataInputStream:close	()V
    //   132: aload 31
    //   134: astore 12
    //   136: aload 12
    //   138: ldc 110
    //   140: invokevirtual 114	java/lang/String:indexOf	(Ljava/lang/String;)I
    //   143: iconst_m1
    //   144: if_icmple +384 -> 528
    //   147: ldc 116
    //   149: astore 12
    //   151: aload_3
    //   152: iconst_1
    //   153: aload_3
    //   154: bipush 47
    //   156: invokevirtual 120	java/lang/String:lastIndexOf	(I)I
    //   159: iadd
    //   160: aload_3
    //   161: invokevirtual 91	java/lang/String:length	()I
    //   164: invokevirtual 124	java/lang/String:substring	(II)Ljava/lang/String;
    //   167: astore 13
    //   169: new 126	java/lang/StringBuilder
    //   172: dup
    //   173: invokestatic 131	com/zing/zalo/g/a:hd	()Ljava/lang/String;
    //   176: invokestatic 134	java/lang/String:valueOf	(Ljava/lang/Object;)Ljava/lang/String;
    //   179: invokespecial 135	java/lang/StringBuilder:<init>	(Ljava/lang/String;)V
    //   182: aload 13
    //   184: invokevirtual 139	java/lang/StringBuilder:append	(Ljava/lang/String;)Ljava/lang/StringBuilder;
    //   187: aload 12
    //   189: invokevirtual 139	java/lang/StringBuilder:append	(Ljava/lang/String;)Ljava/lang/StringBuilder;
    //   192: invokevirtual 142	java/lang/StringBuilder:toString	()Ljava/lang/String;
    //   195: astore 14
    //   197: new 84	java/io/File
    //   200: dup
    //   201: aload_3
    //   202: invokespecial 143	java/io/File:<init>	(Ljava/lang/String;)V
    //   205: astore 15
    //   207: new 84	java/io/File
    //   210: dup
    //   211: aload 14
    //   213: invokespecial 143	java/io/File:<init>	(Ljava/lang/String;)V
    //   216: astore 16
    //   218: aload 15
    //   220: invokevirtual 147	java/io/File:exists	()Z
    //   223: ifeq +63 -> 286
    //   226: aload 16
    //   228: invokevirtual 147	java/io/File:exists	()Z
    //   231: ifne +55 -> 286
    //   234: new 95	java/io/FileInputStream
    //   237: dup
    //   238: aload 15
    //   240: invokespecial 150	java/io/FileInputStream:<init>	(Ljava/io/File;)V
    //   243: invokevirtual 154	java/io/FileInputStream:getChannel	()Ljava/nio/channels/FileChannel;
    //   246: astore 17
    //   248: new 156	java/io/FileOutputStream
    //   251: dup
    //   252: aload 16
    //   254: invokespecial 157	java/io/FileOutputStream:<init>	(Ljava/io/File;)V
    //   257: invokevirtual 158	java/io/FileOutputStream:getChannel	()Ljava/nio/channels/FileChannel;
    //   260: astore 18
    //   262: aload 18
    //   264: aload 17
    //   266: lconst_0
    //   267: aload 17
    //   269: invokevirtual 164	java/nio/channels/FileChannel:size	()J
    //   272: invokevirtual 168	java/nio/channels/FileChannel:transferFrom	(Ljava/nio/channels/ReadableByteChannel;JJ)J
    //   275: pop2
    //   276: aload 17
    //   278: invokevirtual 169	java/nio/channels/FileChannel:close	()V
    //   281: aload 18
    //   283: invokevirtual 169	java/nio/channels/FileChannel:close	()V
    //   286: aload 16
    //   288: invokevirtual 147	java/io/File:exists	()Z
    //   291: ifeq +273 -> 564
    //   294: aload_0
    //   295: getfield 12	com/zing/zalo/ui/rh:ajd	Lcom/zing/zalo/ui/ImageViewActivity;
    //   298: aload 14
    //   300: invokestatic 172	com/zing/zalo/ui/ImageViewActivity:b	(Lcom/zing/zalo/ui/ImageViewActivity;Ljava/lang/String;)V
    //   303: return
    //   304: aload 5
    //   306: iload 7
    //   308: aload 6
    //   310: invokevirtual 176	java/io/DataInputStream:readByte	()B
    //   313: i2c
    //   314: castore
    //   315: iinc 7 1
    //   318: goto -210 -> 108
    //   321: astore 33
    //   323: aconst_null
    //   324: astore 6
    //   326: getstatic 182	java/lang/System:out	Ljava/io/PrintStream;
    //   329: ldc 184
    //   331: invokevirtual 189	java/io/PrintStream:println	(Ljava/lang/String;)V
    //   334: aload 6
    //   336: ifnull +315 -> 651
    //   339: aload 6
    //   341: invokevirtual 108	java/io/DataInputStream:close	()V
    //   344: ldc 191
    //   346: astore 12
    //   348: goto -212 -> 136
    //   351: astore 21
    //   353: ldc 191
    //   355: astore 12
    //   357: goto -221 -> 136
    //   360: astore 23
    //   362: getstatic 194	java/lang/System:err	Ljava/io/PrintStream;
    //   365: new 126	java/lang/StringBuilder
    //   368: dup
    //   369: ldc 196
    //   371: invokespecial 135	java/lang/StringBuilder:<init>	(Ljava/lang/String;)V
    //   374: aload 23
    //   376: invokevirtual 199	java/lang/StringBuilder:append	(Ljava/lang/Object;)Ljava/lang/StringBuilder;
    //   379: invokevirtual 142	java/lang/StringBuilder:toString	()Ljava/lang/String;
    //   382: invokevirtual 189	java/io/PrintStream:println	(Ljava/lang/String;)V
    //   385: aload 4
    //   387: ifnull +264 -> 651
    //   390: aload 4
    //   392: invokevirtual 108	java/io/DataInputStream:close	()V
    //   395: ldc 191
    //   397: astore 12
    //   399: goto -263 -> 136
    //   402: astore 24
    //   404: ldc 191
    //   406: astore 12
    //   408: goto -272 -> 136
    //   411: astore 26
    //   413: getstatic 194	java/lang/System:err	Ljava/io/PrintStream;
    //   416: new 126	java/lang/StringBuilder
    //   419: dup
    //   420: ldc 201
    //   422: invokespecial 135	java/lang/StringBuilder:<init>	(Ljava/lang/String;)V
    //   425: aload 26
    //   427: invokevirtual 199	java/lang/StringBuilder:append	(Ljava/lang/Object;)Ljava/lang/StringBuilder;
    //   430: invokevirtual 142	java/lang/StringBuilder:toString	()Ljava/lang/String;
    //   433: invokevirtual 189	java/io/PrintStream:println	(Ljava/lang/String;)V
    //   436: aload 4
    //   438: ifnull +213 -> 651
    //   441: aload 4
    //   443: invokevirtual 108	java/io/DataInputStream:close	()V
    //   446: ldc 191
    //   448: astore 12
    //   450: goto -314 -> 136
    //   453: astore 27
    //   455: ldc 191
    //   457: astore 12
    //   459: goto -323 -> 136
    //   462: astore 29
    //   464: getstatic 194	java/lang/System:err	Ljava/io/PrintStream;
    //   467: new 126	java/lang/StringBuilder
    //   470: dup
    //   471: ldc 203
    //   473: invokespecial 135	java/lang/StringBuilder:<init>	(Ljava/lang/String;)V
    //   476: aload 29
    //   478: invokevirtual 199	java/lang/StringBuilder:append	(Ljava/lang/Object;)Ljava/lang/StringBuilder;
    //   481: invokevirtual 142	java/lang/StringBuilder:toString	()Ljava/lang/String;
    //   484: invokevirtual 189	java/io/PrintStream:println	(Ljava/lang/String;)V
    //   487: aload 4
    //   489: ifnull +162 -> 651
    //   492: aload 4
    //   494: invokevirtual 108	java/io/DataInputStream:close	()V
    //   497: ldc 191
    //   499: astore 12
    //   501: goto -365 -> 136
    //   504: astore 30
    //   506: ldc 191
    //   508: astore 12
    //   510: goto -374 -> 136
    //   513: astore 10
    //   515: aload 4
    //   517: ifnull +8 -> 525
    //   520: aload 4
    //   522: invokevirtual 108	java/io/DataInputStream:close	()V
    //   525: aload 10
    //   527: athrow
    //   528: aload 12
    //   530: ldc 205
    //   532: invokevirtual 114	java/lang/String:indexOf	(Ljava/lang/String;)I
    //   535: iconst_m1
    //   536: if_icmple +10 -> 546
    //   539: ldc 207
    //   541: astore 12
    //   543: goto -392 -> 151
    //   546: aload 12
    //   548: ldc 209
    //   550: invokevirtual 114	java/lang/String:indexOf	(Ljava/lang/String;)I
    //   553: iconst_m1
    //   554: if_icmple -403 -> 151
    //   557: ldc 211
    //   559: astore 12
    //   561: goto -410 -> 151
    //   564: aload_0
    //   565: getfield 12	com/zing/zalo/ui/rh:ajd	Lcom/zing/zalo/ui/ImageViewActivity;
    //   568: aload_3
    //   569: invokestatic 172	com/zing/zalo/ui/ImageViewActivity:b	(Lcom/zing/zalo/ui/ImageViewActivity;Ljava/lang/String;)V
    //   572: return
    //   573: aload_0
    //   574: getfield 12	com/zing/zalo/ui/rh:ajd	Lcom/zing/zalo/ui/ImageViewActivity;
    //   577: aload_2
    //   578: invokestatic 172	com/zing/zalo/ui/ImageViewActivity:b	(Lcom/zing/zalo/ui/ImageViewActivity;Ljava/lang/String;)V
    //   581: return
    //   582: astore 11
    //   584: goto -59 -> 525
    //   587: astore 9
    //   589: aload 6
    //   591: astore 4
    //   593: aload 9
    //   595: astore 10
    //   597: goto -82 -> 515
    //   600: astore 28
    //   602: aload 6
    //   604: astore 4
    //   606: aload 28
    //   608: astore 29
    //   610: goto -146 -> 464
    //   613: astore 25
    //   615: aload 6
    //   617: astore 4
    //   619: aload 25
    //   621: astore 26
    //   623: goto -210 -> 413
    //   626: astore 22
    //   628: aload 6
    //   630: astore 4
    //   632: aload 22
    //   634: astore 23
    //   636: goto -274 -> 362
    //   639: astore 8
    //   641: goto -315 -> 326
    //   644: aload 31
    //   646: astore 12
    //   648: goto -512 -> 136
    //   651: ldc 191
    //   653: astore 12
    //   655: goto -519 -> 136
    //   658: astore_1
    //   659: return
    //   660: astore 32
    //   662: aload 31
    //   664: astore 12
    //   666: goto -530 -> 136
    //
    // Exception table:
    //   from	to	target	type
    //   88	105	321	java/io/EOFException
    //   339	344	351	java/io/IOException
    //   88	105	360	java/io/FileNotFoundException
    //   390	395	402	java/io/IOException
    //   88	105	411	java/io/IOException
    //   441	446	453	java/io/IOException
    //   88	105	462	java/lang/Throwable
    //   492	497	504	java/io/IOException
    //   88	105	513	finally
    //   362	385	513	finally
    //   413	436	513	finally
    //   464	487	513	finally
    //   520	525	582	java/io/IOException
    //   115	122	587	finally
    //   304	315	587	finally
    //   326	334	587	finally
    //   115	122	600	java/lang/Throwable
    //   304	315	600	java/lang/Throwable
    //   115	122	613	java/io/IOException
    //   304	315	613	java/io/IOException
    //   115	122	626	java/io/FileNotFoundException
    //   304	315	626	java/io/FileNotFoundException
    //   115	122	639	java/io/EOFException
    //   304	315	639	java/io/EOFException
    //   0	79	658	java/lang/Exception
    //   82	88	658	java/lang/Exception
    //   127	132	658	java/lang/Exception
    //   136	147	658	java/lang/Exception
    //   151	286	658	java/lang/Exception
    //   286	303	658	java/lang/Exception
    //   339	344	658	java/lang/Exception
    //   390	395	658	java/lang/Exception
    //   441	446	658	java/lang/Exception
    //   492	497	658	java/lang/Exception
    //   520	525	658	java/lang/Exception
    //   525	528	658	java/lang/Exception
    //   528	539	658	java/lang/Exception
    //   546	557	658	java/lang/Exception
    //   564	572	658	java/lang/Exception
    //   573	581	658	java/lang/Exception
    //   127	132	660	java/io/IOException
  }
}

/* Location:           /home/danghvu/0day/Zalo/Zalo_1.0.8_dex2jar.jar
 * Qualified Name:     com.zing.zalo.ui.rh
 * JD-Core Version:    0.6.2
 */