package unk.com.zing.zalo.j;

class i extends g
{
  private final j LN = new j(this);

  // ERROR //
  protected h a(java.lang.CharSequence paramCharSequence, int paramInt)
  {
    // Byte code:
    //   0: aload_0
    //   1: getfield 17	com/zing/zalo/j/i:LN	Lcom/zing/zalo/j/j;
    //   4: astore_3
    //   5: iconst_m1
    //   6: istore 4
    //   8: iconst_0
    //   9: istore 5
    //   11: aconst_null
    //   12: astore 6
    //   14: aload_1
    //   15: invokeinterface 27 1 0
    //   20: istore 7
    //   22: iload_2
    //   23: istore 8
    //   25: iload 8
    //   27: iload 7
    //   29: if_icmplt +21 -> 50
    //   32: aload 6
    //   34: ifnull +302 -> 336
    //   37: new 29	com/zing/zalo/j/h
    //   40: dup
    //   41: aload_0
    //   42: iload 4
    //   44: iload 5
    //   46: invokespecial 32	com/zing/zalo/j/h:<init>	(Lcom/zing/zalo/j/g;II)V
    //   49: areturn
    //   50: aload_1
    //   51: iload 8
    //   53: invokeinterface 36 2 0
    //   58: istore 10
    //   60: iload 10
    //   62: bipush 32
    //   64: if_icmple +336 -> 400
    //   67: iload 10
    //   69: bipush 127
    //   71: if_icmpgt +329 -> 400
    //   74: aload_3
    //   75: aload_0
    //   76: getfield 17	com/zing/zalo/j/i:LN	Lcom/zing/zalo/j/j;
    //   79: if_acmpne +7 -> 86
    //   82: iload 8
    //   84: istore 4
    //   86: aload_3
    //   87: checkcast 12	com/zing/zalo/j/j
    //   90: getfield 40	com/zing/zalo/j/j:LO	[Lcom/zing/zalo/j/j;
    //   93: ifnull +290 -> 383
    //   96: aload_3
    //   97: checkcast 12	com/zing/zalo/j/j
    //   100: getfield 40	com/zing/zalo/j/j:LO	[Lcom/zing/zalo/j/j;
    //   103: astore 26
    //   105: iload 10
    //   107: bipush 32
    //   109: isub
    //   110: istore 27
    //   112: aload 26
    //   114: iload 27
    //   116: aaload
    //   117: ifnull +266 -> 383
    //   120: aload 26
    //   122: iload 27
    //   124: aaload
    //   125: astore 28
    //   127: aload 28
    //   129: checkcast 12	com/zing/zalo/j/j
    //   132: getfield 44	com/zing/zalo/j/j:LP	Z
    //   135: istore 29
    //   137: iload 29
    //   139: ifeq +117 -> 256
    //   142: iconst_1
    //   143: iload 8
    //   145: iload 4
    //   147: isub
    //   148: iadd
    //   149: istore 5
    //   151: iload 8
    //   153: iload 7
    //   155: iconst_1
    //   156: isub
    //   157: if_icmpge +208 -> 365
    //   160: iload 8
    //   162: iconst_1
    //   163: iadd
    //   164: istore 30
    //   166: aload_1
    //   167: iload 30
    //   169: invokeinterface 36 2 0
    //   174: istore 32
    //   176: iload 32
    //   178: bipush 32
    //   180: isub
    //   181: istore 33
    //   183: iload 32
    //   185: bipush 32
    //   187: if_icmple +178 -> 365
    //   190: iload 32
    //   192: bipush 127
    //   194: if_icmpgt +171 -> 365
    //   197: aload 26
    //   199: iload 33
    //   201: aaload
    //   202: ifnull +163 -> 365
    //   205: aload 26
    //   207: iload 33
    //   209: aaload
    //   210: getfield 44	com/zing/zalo/j/j:LP	Z
    //   213: istore 34
    //   215: iload 34
    //   217: ifeq +148 -> 365
    //   220: aload 28
    //   222: astore 15
    //   224: iload 5
    //   226: istore 20
    //   228: iconst_1
    //   229: istore 21
    //   231: aload 28
    //   233: astore 19
    //   235: iload 21
    //   237: ifne +189 -> 426
    //   240: aload 19
    //   242: ifnull +32 -> 274
    //   245: aload 19
    //   247: astore 6
    //   249: iload 20
    //   251: istore 5
    //   253: goto -221 -> 32
    //   256: aload 6
    //   258: astore 19
    //   260: aload 28
    //   262: astore 15
    //   264: iload 5
    //   266: istore 20
    //   268: iconst_1
    //   269: istore 21
    //   271: goto -36 -> 235
    //   274: aload_0
    //   275: getfield 17	com/zing/zalo/j/i:LN	Lcom/zing/zalo/j/j;
    //   278: astore 24
    //   280: aload 24
    //   282: astore 15
    //   284: iload 4
    //   286: istore 12
    //   288: iload 20
    //   290: istore 25
    //   292: aload 19
    //   294: astore 16
    //   296: iload 4
    //   298: istore 11
    //   300: iload 25
    //   302: istore 13
    //   304: iload 11
    //   306: iconst_1
    //   307: iadd
    //   308: istore 17
    //   310: iload 13
    //   312: istore 5
    //   314: iload 12
    //   316: istore 4
    //   318: iload 17
    //   320: istore 8
    //   322: aload 16
    //   324: astore 18
    //   326: aload 15
    //   328: astore_3
    //   329: aload 18
    //   331: astore 6
    //   333: goto -308 -> 25
    //   336: aconst_null
    //   337: areturn
    //   338: astore 31
    //   340: aload 28
    //   342: astore 6
    //   344: goto -312 -> 32
    //   347: astore 23
    //   349: aload 19
    //   351: astore 6
    //   353: iload 20
    //   355: istore 5
    //   357: goto -325 -> 32
    //   360: astore 9
    //   362: goto -330 -> 32
    //   365: aload 28
    //   367: astore 19
    //   369: aload 28
    //   371: astore 15
    //   373: iload 5
    //   375: istore 20
    //   377: iconst_0
    //   378: istore 21
    //   380: goto -145 -> 235
    //   383: aload 6
    //   385: astore 19
    //   387: aload_3
    //   388: astore 15
    //   390: iload 5
    //   392: istore 20
    //   394: iconst_0
    //   395: istore 21
    //   397: goto -162 -> 235
    //   400: iload 8
    //   402: istore 11
    //   404: iload 4
    //   406: istore 12
    //   408: iload 5
    //   410: istore 13
    //   412: aload 6
    //   414: astore 14
    //   416: aload_3
    //   417: astore 15
    //   419: aload 14
    //   421: astore 16
    //   423: goto -119 -> 304
    //   426: iload 8
    //   428: istore 22
    //   430: iload 4
    //   432: istore 12
    //   434: iload 20
    //   436: istore 13
    //   438: aload 19
    //   440: astore 16
    //   442: iload 22
    //   444: istore 11
    //   446: goto -142 -> 304
    //
    // Exception table:
    //   from	to	target	type
    //   166	176	338	java/lang/Exception
    //   197	215	338	java/lang/Exception
    //   274	280	347	java/lang/Exception
    //   50	60	360	java/lang/Exception
    //   74	82	360	java/lang/Exception
    //   86	105	360	java/lang/Exception
    //   112	137	360	java/lang/Exception
  }

  public void cN(String paramString)
  {
    this.LN.cN(paramString);
  }
}

/* Location:           /home/danghvu/0day/Zalo/Zalo_1.0.8_dex2jar.jar
 * Qualified Name:     com.zing.zalo.j.i
 * JD-Core Version:    0.6.2
 */