package unk.com.zing.zalo.minigame;

class m
  implements Runnable
{
  m(l paraml)
  {
  }

  // ERROR //
  public void run()
  {
    // Byte code:
    //   0: aload_0
    //   1: getfield 12	com/zing/zalo/minigame/m:Lj	Lcom/zing/zalo/minigame/l;
    //   4: invokestatic 24	com/zing/zalo/minigame/l:a	(Lcom/zing/zalo/minigame/l;)Lcom/zing/zalo/minigame/DrawSomething;
    //   7: invokestatic 30	com/zing/zalo/minigame/DrawSomething:b	(Lcom/zing/zalo/minigame/DrawSomething;)Lcom/zing/zalo/uicontrol/WordPickerView;
    //   10: iconst_0
    //   11: invokevirtual 36	com/zing/zalo/uicontrol/WordPickerView:setBlinking	(Z)V
    //   14: getstatic 42	com/zing/zalo/ui/ChatActivity:acm	Ljava/lang/String;
    //   17: ldc 44
    //   19: invokevirtual 50	java/lang/String:equals	(Ljava/lang/Object;)Z
    //   22: ifne +74 -> 96
    //   25: getstatic 54	com/zing/zalo/ui/ChatActivity:acn	Lcom/zing/zalo/control/m;
    //   28: ifnull +68 -> 96
    //   31: ldc 44
    //   33: astore_2
    //   34: invokestatic 60	com/zing/zalo/db/a:hn	()Lcom/zing/zalo/db/a;
    //   37: getstatic 54	com/zing/zalo/ui/ChatActivity:acn	Lcom/zing/zalo/control/m;
    //   40: getfield 65	com/zing/zalo/control/m:xU	Ljava/lang/String;
    //   43: invokevirtual 69	com/zing/zalo/db/a:bn	(Ljava/lang/String;)Ljava/lang/String;
    //   46: astore 4
    //   48: aload 4
    //   50: astore_2
    //   51: new 71	java/lang/StringBuilder
    //   54: dup
    //   55: getstatic 54	com/zing/zalo/ui/ChatActivity:acn	Lcom/zing/zalo/control/m;
    //   58: getfield 74	com/zing/zalo/control/m:xV	Ljava/lang/String;
    //   61: invokestatic 78	java/lang/String:valueOf	(Ljava/lang/Object;)Ljava/lang/String;
    //   64: invokespecial 81	java/lang/StringBuilder:<init>	(Ljava/lang/String;)V
    //   67: ldc 83
    //   69: invokevirtual 87	java/lang/StringBuilder:append	(Ljava/lang/String;)Ljava/lang/StringBuilder;
    //   72: getstatic 90	com/zing/zalo/ui/ChatActivity:Lg	Ljava/lang/String;
    //   75: invokevirtual 94	java/lang/String:toUpperCase	()Ljava/lang/String;
    //   78: invokevirtual 87	java/lang/StringBuilder:append	(Ljava/lang/String;)Ljava/lang/StringBuilder;
    //   81: ldc 96
    //   83: invokevirtual 87	java/lang/StringBuilder:append	(Ljava/lang/String;)Ljava/lang/StringBuilder;
    //   86: aload_2
    //   87: invokevirtual 87	java/lang/StringBuilder:append	(Ljava/lang/String;)Ljava/lang/StringBuilder;
    //   90: invokevirtual 99	java/lang/StringBuilder:toString	()Ljava/lang/String;
    //   93: putstatic 42	com/zing/zalo/ui/ChatActivity:acm	Ljava/lang/String;
    //   96: aload_0
    //   97: getfield 12	com/zing/zalo/minigame/m:Lj	Lcom/zing/zalo/minigame/l;
    //   100: invokestatic 24	com/zing/zalo/minigame/l:a	(Lcom/zing/zalo/minigame/l;)Lcom/zing/zalo/minigame/DrawSomething;
    //   103: iconst_3
    //   104: invokevirtual 103	com/zing/zalo/minigame/DrawSomething:showDialog	(I)V
    //   107: return
    //   108: astore_1
    //   109: aload_1
    //   110: invokevirtual 106	java/lang/Exception:printStackTrace	()V
    //   113: return
    //   114: astore_3
    //   115: goto -64 -> 51
    //
    // Exception table:
    //   from	to	target	type
    //   0	31	108	java/lang/Exception
    //   51	96	108	java/lang/Exception
    //   96	107	108	java/lang/Exception
    //   34	48	114	java/lang/Exception
  }
}

/* Location:           /home/danghvu/0day/Zalo/Zalo_1.0.8_dex2jar.jar
 * Qualified Name:     com.zing.zalo.minigame.m
 * JD-Core Version:    0.6.2
 */