package unk.com.zing.zalo.social;

class el
  implements Runnable
{
  el(ImagePickerActivity paramImagePickerActivity)
  {
  }

  // ERROR //
  public void run()
  {
    // Byte code:
    //   0: ldc 22
    //   2: ldc 24
    //   4: invokestatic 30	com/zing/zalo/utils/h:ad	(Ljava/lang/String;Ljava/lang/String;)V
    //   7: iconst_2
    //   8: anewarray 32	java/lang/String
    //   11: dup
    //   12: iconst_0
    //   13: ldc 34
    //   15: aastore
    //   16: dup
    //   17: iconst_1
    //   18: ldc 36
    //   20: aastore
    //   21: astore 4
    //   23: iconst_1
    //   24: anewarray 32	java/lang/String
    //   27: dup
    //   28: iconst_0
    //   29: ldc 38
    //   31: aastore
    //   32: astore 5
    //   34: aload_0
    //   35: getfield 12	com/zing/zalo/social/el:QQ	Lcom/zing/zalo/social/ImagePickerActivity;
    //   38: invokevirtual 44	com/zing/zalo/social/ImagePickerActivity:getContentResolver	()Landroid/content/ContentResolver;
    //   41: getstatic 50	android/provider/MediaStore$Images$Media:EXTERNAL_CONTENT_URI	Landroid/net/Uri;
    //   44: aload 4
    //   46: ldc 52
    //   48: aload 5
    //   50: ldc 54
    //   52: invokevirtual 60	android/content/ContentResolver:query	(Landroid/net/Uri;[Ljava/lang/String;Ljava/lang/String;[Ljava/lang/String;Ljava/lang/String;)Landroid/database/Cursor;
    //   55: astore 6
    //   57: aload 6
    //   59: astore_2
    //   60: aload_2
    //   61: ldc 36
    //   63: invokeinterface 66 2 0
    //   68: istore 7
    //   70: aload_2
    //   71: ldc 34
    //   73: invokeinterface 66 2 0
    //   78: istore 8
    //   80: iconst_2
    //   81: anewarray 32	java/lang/String
    //   84: dup
    //   85: iconst_0
    //   86: ldc 68
    //   88: aastore
    //   89: dup
    //   90: iconst_1
    //   91: ldc 70
    //   93: aastore
    //   94: astore 9
    //   96: aload_2
    //   97: invokeinterface 74 1 0
    //   102: ifne +38 -> 140
    //   105: aload_0
    //   106: getfield 12	com/zing/zalo/social/el:QQ	Lcom/zing/zalo/social/ImagePickerActivity;
    //   109: new 76	com/zing/zalo/social/em
    //   112: dup
    //   113: aload_0
    //   114: invokespecial 79	com/zing/zalo/social/em:<init>	(Lcom/zing/zalo/social/el;)V
    //   117: invokevirtual 83	com/zing/zalo/social/ImagePickerActivity:runOnUiThread	(Ljava/lang/Runnable;)V
    //   120: aload_2
    //   121: ifnull +18 -> 139
    //   124: aload_2
    //   125: invokeinterface 86 1 0
    //   130: ifne +9 -> 139
    //   133: aload_2
    //   134: invokeinterface 89 1 0
    //   139: return
    //   140: aload_2
    //   141: iload 7
    //   143: invokeinterface 93 2 0
    //   148: istore 10
    //   150: aload_2
    //   151: iload 8
    //   153: invokeinterface 97 2 0
    //   158: astore 11
    //   160: aload 11
    //   162: invokevirtual 101	java/lang/String:toLowerCase	()Ljava/lang/String;
    //   165: aload 9
    //   167: iconst_0
    //   168: aaload
    //   169: invokevirtual 105	java/lang/String:endsWith	(Ljava/lang/String;)Z
    //   172: ifne +18 -> 190
    //   175: aload 11
    //   177: invokevirtual 101	java/lang/String:toLowerCase	()Ljava/lang/String;
    //   180: aload 9
    //   182: iconst_1
    //   183: aaload
    //   184: invokevirtual 105	java/lang/String:endsWith	(Ljava/lang/String;)Z
    //   187: ifeq -91 -> 96
    //   190: aload_0
    //   191: getfield 12	com/zing/zalo/social/el:QQ	Lcom/zing/zalo/social/ImagePickerActivity;
    //   194: invokestatic 109	com/zing/zalo/social/ImagePickerActivity:f	(Lcom/zing/zalo/social/ImagePickerActivity;)Ljava/util/ArrayList;
    //   197: iload 10
    //   199: invokestatic 115	java/lang/Integer:valueOf	(I)Ljava/lang/Integer;
    //   202: invokevirtual 121	java/util/ArrayList:add	(Ljava/lang/Object;)Z
    //   205: pop
    //   206: aload_0
    //   207: getfield 12	com/zing/zalo/social/el:QQ	Lcom/zing/zalo/social/ImagePickerActivity;
    //   210: invokestatic 124	com/zing/zalo/social/ImagePickerActivity:g	(Lcom/zing/zalo/social/ImagePickerActivity;)Ljava/util/ArrayList;
    //   213: aload 11
    //   215: invokevirtual 121	java/util/ArrayList:add	(Ljava/lang/Object;)Z
    //   218: pop
    //   219: goto -123 -> 96
    //   222: astore_1
    //   223: aload_1
    //   224: invokevirtual 127	java/lang/Exception:printStackTrace	()V
    //   227: aload_2
    //   228: ifnull -89 -> 139
    //   231: aload_2
    //   232: invokeinterface 86 1 0
    //   237: ifne -98 -> 139
    //   240: aload_2
    //   241: invokeinterface 89 1 0
    //   246: return
    //   247: astore_3
    //   248: aconst_null
    //   249: astore_2
    //   250: aload_2
    //   251: ifnull +18 -> 269
    //   254: aload_2
    //   255: invokeinterface 86 1 0
    //   260: ifne +9 -> 269
    //   263: aload_2
    //   264: invokeinterface 89 1 0
    //   269: aload_3
    //   270: athrow
    //   271: astore_3
    //   272: goto -22 -> 250
    //   275: astore_1
    //   276: aconst_null
    //   277: astore_2
    //   278: goto -55 -> 223
    //
    // Exception table:
    //   from	to	target	type
    //   60	96	222	java/lang/Exception
    //   96	120	222	java/lang/Exception
    //   140	190	222	java/lang/Exception
    //   190	219	222	java/lang/Exception
    //   0	57	247	finally
    //   60	96	271	finally
    //   96	120	271	finally
    //   140	190	271	finally
    //   190	219	271	finally
    //   223	227	271	finally
    //   0	57	275	java/lang/Exception
  }
}

/* Location:           /home/danghvu/0day/Zalo/Zalo_1.0.8_dex2jar.jar
 * Qualified Name:     com.zing.zalo.social.el
 * JD-Core Version:    0.6.2
 */